Workbook
Name _Inciso_Apoyo: 'Oferta Vinculante'!$M$44
Name _Inciso_Cofinavit: 'Oferta Vinculante'!$M$38
Name _Inciso_Gravamen_Separado: 'Oferta Vinculante'!$M$29
Name _Inciso_Vigilancia: 'Oferta Vinculante'!$M$25
Name A: #REF!
Name A: #REF!
Name A: #REF!
Name Aforo: 'Oferta Vinculante'!$M$13
Name Aforo_3_Fovissste: #REF!
Name Aforo_3_Fovissste: #REF!
Name Aforo_3_Fovissste: #REF!
Name Aforo_Accesible: #REF!
Name Aforo_Accesible: #REF!
Name Aforo_Accesible: #REF!
Name Aforo_Máximo: #REF!
Name Aforo_Máximo: #REF!
Name Aforo_Máximo: #REF!
Name Aforo_Máximo_2: #REF!
Name Aforo_Máximo_2: #REF!
Name Aforo_Máximo_2: #REF!
Name Aforo_Máximo_A_Usar_Apoyo: #REF!
Name Aforo_Máximo_A_Usar_Apoyo: #REF!
Name Aforo_Máximo_A_Usar_Apoyo: #REF!
Name Aforo_Máximo_A_Usar_Tradicional: #REF!
Name Aforo_Máximo_A_Usar_Tradicional: #REF!
Name Aforo_Máximo_A_Usar_Tradicional: #REF!
Name Aforo_Máximo_del_Layout: #REF!
Name Aforo_Máximo_del_Layout: #REF!
Name Aforo_Máximo_del_Layout: #REF!
Name Aforo3_Cofin: #REF!
Name Aforo3_Cofin: #REF!
Name Aforo3_Cofin: #REF!
Name Alia2_: #REF!
Name Alia2_: #REF!
Name Alia2_: #REF!
Name Amplio: #REF!
Name Amplio: #REF!
Name Amplio: #REF!
Name Anterior: 'Fecha Pago'!1048576:1048576
Name Anualidades_Remanente_SSV: #REF!
Name Anualidades_Remanente_SSV: #REF!
Name Anualidades_Remanente_SSV: #REF!
Name Año_Cotización: #REF!
Name Año_Cotización: #REF!
Name Año_Cotización: #REF!
Name Año_Fecha_Cotización: #REF!
Name Año_Fecha_Cotización: #REF!
Name Año_Fecha_Cotización: #REF!
Name AObD: #REF!
Name AObD: #REF!
Name AObD: #REF!
Name AObT: #REF!
Name AObT: #REF!
Name AObT: #REF!
Name AOp: #REF!
Name AOp: #REF!
Name AOp: #REF!
Name Aplica_IVA?: #REF!
Name Aplica_IVA?: #REF!
Name Aplica_IVA?: #REF!

Sheet Carátula
K2: Nombre del cliente
B4: Simulador Crédito Hipotecario
B5: Datos del Crédito
D7: Fecha de cotización | F7: 45973 | L7: Tipo de seguro | N7: Básico
D9: Destino | F9: Mejora Más Liquidez | I9: ¿El destino anterior causa IVA? | L9: Plazo en meses | N9: 240
D11: Producto | F11: Hipoteca Fuerte | I11: NO | L11: Contratación crédito financiada | N11: NO
D13: Programa | F13: Tradicional | L13: Estado | N13: Ciudad de México
D15: Ingresa valor de vivienda | F15: 1020000 | L15: Aforo Mejora | N15: =F19/F15 -> 0.58823529
D17: *Suma asegurable | F17: =F15*0.7 -> 714000 | L17: Aforo Liquidez | N17: =F21/F15 -> 0.24509804
D19: Monto Mejora de Hipoteca | F19: 600000 | I19: Monto máximo para Liquidez | L19: Aforo Total | N19: =N15+N17 -> 0.83333333
D21: Monto para Liquidez | F21: 250000 | I21: =Catálogos!$N$24 -> 267000 | M21: =IF(N19>Catálogos!K13,Catálogos!J13,"")
B23: *Es el valor comercial menos el valor terreno
B24: Condiciones Financieras
G25: Producto: | H25: =F11 -> Hipoteca Fuerte
G26: Valor Vivienda: | H26: =F15 -> 1020000 | K26: Contratación crédito: | L26: 0
G27: Crédito Mejora: | H27: =F19 -> 600000 | K27: Avalúo hipotecario: | L27: =Avalúos!I6*1.16 -> 0 | M27: IVA Incluido
G28: Crédito Liquidez: | H28: =F21 -> 250000 | K28: *Honorarios Notariales Mejora: | L28: ='Notariales Estados'!$G$1 -> 12931.034 | M28: Sin IVA Incluido
G29: Plazo en meses: | H29: =N9 -> 240 | K29: *Gastos Notariales Liquidez: | L29: =F21*H30 -> 5500 | M29: Sin IVA Incluido
B30: *Se sugiere seleccionar este porcentaje y/o monto, el monto definitivo lo informa el notario previo a la firma del contrato de crédito. | G30: *Gastos Notariales: | H30: ='Notariales Estados'!$E$1 -> 0.022 | K30: Gastos de aprobación: | L30: 750
G31: Seguro Cobertura: | H31: =N7 -> Básico | K31: Enganche: | L31: 0
G32: Desembolso Inicial Estimado: | L32: =SUM(L26:L31) -> 19181.034
I34: Tabla de Pagos a Visualizar
I35: Mejora de Hipoteca
B37: ="Tabla de Pagos "&I35 -> Tabla de Pagos Mejora de Hipoteca
B39: Selecciona la Tasa de interés | E39: 0.0915 | L39: Tipo de prepago | N39: Reduce Plazo y Pago
B41: CAT Promedio | D41: =CAT!$K$8 -> 0.11779232 | E41: Sin IVA Informativo | L41: Su crédito se amortizará en | M41: =COUNT(Q44:Q283) -> 240 | N41: meses
B43: No. | C43: Fecha | D43: Días | E43: Tasa | F43: Saldo Inicial | G43: Capital | H43: Interés | I43: =IF(OR(I11="SI",I35="Liquidez"),"IVA de intereses","") | J43: Seguro de Vida | K43: Seguro de Daños y Contenidos | L43: Administración - autorización de crédito diferido | M43: Aportación a Capital | O43: Pago Mensual | P43: Saldo Final
B44: 1 | C44: =IF(B44="","",'Fecha Pago'!K4) -> 45994 | D44: =IF(B44="","",'Fecha Pago'!L4) -> 22 | E44: =IF(B44="","",$E$39) -> 0.0915 | F44: =IF(Catálogos!$R$12=1,Carátula!$H$27,Carátula!$H$28) -> 600000 | G44: =IF(B44="","",IF(F44=0,0,MIN(F44,IF(Catálogos!$N$6=1,Prepagos!C3,IF(Catálogos!$N$6=2,Prepagos!D3,IF(Catálogos!$N$6=3,Prepagos!E3,)))))) -> 867.75904 | H44: =IF(B44="","",IF(F44=0,0,(E44/360*D44)*F44)) -> 3355 | I44: =IF(B44="","",IF($I$43<>"",H44*0.16,0)) -> 0 | J44: =IF(B44="","",IF(F44=0,0,F44*(Catálogos!$R$1)/30*D44)) -> 264 | K44: =IF(B44="","",IF(Catálogos!$K$10=1,Carátula!$F$17*Catálogos!$R$4/30*D44,0)) -> 146.608 | L44: =IF(B44="","",IF(F44=0,0,CAT!H7)) -> 299 | N44: =IF(B44="","",IF(M44>0,M44-(M44/(1+Catálogos!$N$10)),0)) -> 0 | O44: =IF(B44="","",G44+H44+I44+J44+K44+L44) -> 4932.367 | P44: =IF(B44="","",F44-G44) -> 599132.24 | Q44: =IF(OR(B44="",F44=0),"",1) -> 1
B45: =IF(B44=$H$29,"",IF(B44="","",B44+1)) -> 2 | C45: =IF(B45="","",'Fecha Pago'!K5) -> 46025 | D45: =IF(B45="","",'Fecha Pago'!L5) -> 30.4 | E45: =IF(B45="","",$E$39) -> 0.0915 | F45: =IF(B45="","",P44) -> 599132.24 | G45: =IF(B45="","",IF(F45=0,0,MIN(F45,IF(Catálogos!$N$6=1,Prepagos!C4,IF(Catálogos!$N$6=2,Prepagos!D4,IF(Catálogos!$N$6=3,Prepagos!E4,)))))) -> 874.46393 | H45: =IF(B45="","",IF(F45=0,0,(E45/360*D45)*F45)) -> 4629.2951 | I45: =IF(B45="","",IF($I$43<>"",H45*0.16,0)) -> 0 | J45: =IF(B45="","",IF(F45=0,0,F45*Catálogos!$R$1)) -> 359.47934 | K45: =IF(B45="","",IF(Catálogos!$K$10=1,Carátula!$F$17*Catálogos!$R$4,0)) -> 199.92 | L45: =IF(B45="","",IF(F45=0,0,CAT!H8)) -> 299 | N45: =IF(B45="","",IF(M45>0,M45-(M45/(1+Catálogos!$N$10)),0)) -> 0 | O45: =IF(B45="","",G45+H45+I45+J45+K45+L45) -> 6362.1584 | P45: =IF(B45="","",F45-G45) -> 598257.78 | Q45: =IF(OR(B45="",F45=0),"",1) -> 1
B46: =IF(B45=$H$29,"",IF(B45="","",B45+1)) -> 3 | C46: =IF(B46="","",'Fecha Pago'!K6) -> 46056 | D46: =IF(B46="","",'Fecha Pago'!L6) -> 30.4 | E46: =IF(B46="","",$E$39) -> 0.0915 | F46: =IF(B46="","",P45) -> 598257.78 | G46: =IF(B46="","",IF(F46=0,0,MIN(F46,IF(Catálogos!$N$6=1,Prepagos!C5,IF(Catálogos!$N$6=2,Prepagos!D5,IF(Catálogos!$N$6=3,Prepagos!E5,)))))) -> 881.22062 | H46: =IF(B46="","",IF(F46=0,0,(E46/360*D46)*F46)) -> 4622.5384 | I46: =IF(B46="","",IF($I$43<>"",H46*0.16,0)) -> 0 | J46: =IF(B46="","",IF(F46=0,0,F46*Catálogos!$R$1)) -> 358.95467 | K46: =IF(B46="","",IF(Catálogos!$K$10=1,Carátula!$F$17*Catálogos!$R$4,0)) -> 199.92 | L46: =IF(B46="","",IF(F46=0,0,CAT!H9)) -> 299 | N46: =IF(B46="","",IF(M46>0,M46-(M46/(1+Catálogos!$N$10)),0)) -> 0 | O46: =IF(B46="","",G46+H46+I46+J46+K46+L46) -> 6361.6337 | P46: =IF(B46="","",F46-G46) -> 597376.56 | Q46: =IF(OR(B46="",F46=0),"",1) -> 1
B47: =IF(B46=$H$29,"",IF(B46="","",B46+1)) -> 4 | C47: =IF(B47="","",'Fecha Pago'!K7) -> 46084 | D47: =IF(B47="","",'Fecha Pago'!L7) -> 30.4 | E47: =IF(B47="","",$E$39) -> 0.0915 | F47: =IF(B47="","",P46) -> 597376.56 | G47: =IF(B47="","",IF(F47=0,0,MIN(F47,IF(Catálogos!$N$6=1,Prepagos!C6,IF(Catálogos!$N$6=2,Prepagos!D6,IF(Catálogos!$N$6=3,Prepagos!E6,)))))) -> 888.02952 | H47: =IF(B47="","",IF(F47=0,0,(E47/360*D47)*F47)) -> 4615.7295 | I47: =IF(B47="","",IF($I$43<>"",H47*0.16,0)) -> 0 | J47: =IF(B47="","",IF(F47=0,0,F47*Catálogos!$R$1)) -> 358.42593 | K47: =IF(B47="","",IF(Catálogos!$K$10=1,Carátula!$F$17*Catálogos!$R$4,0)) -> 199.92 | L47: =IF(B47="","",IF(F47=0,0,CAT!H10)) -> 299 | N47: =IF(B47="","",IF(M47>0,M47-(M47/(1+Catálogos!$N$10)),0)) -> 0 | O47: =IF(B47="","",G47+H47+I47+J47+K47+L47) -> 6361.105 | P47: =IF(B47="","",F47-G47) -> 596488.53 | Q47: =IF(OR(B47="",F47=0),"",1) -> 1
B48: =IF(B47=$H$29,"",IF(B47="","",B47+1)) -> 5 | C48: =IF(B48="","",'Fecha Pago'!K8) -> 46115 | D48: =IF(B48="","",'Fecha Pago'!L8) -> 30.4 | E48: =IF(B48="","",$E$39) -> 0.0915 | F48: =IF(B48="","",P47) -> 596488.53 | G48: =IF(B48="","",IF(F48=0,0,MIN(F48,IF(Catálogos!$N$6=1,Prepagos!C7,IF(Catálogos!$N$6=2,Prepagos!D7,IF(Catálogos!$N$6=3,Prepagos!E7,)))))) -> 894.89102 | H48: =IF(B48="","",IF(F48=0,0,(E48/360*D48)*F48)) -> 4608.868 | I48: =IF(B48="","",IF($I$43<>"",H48*0.16,0)) -> 0 | J48: =IF(B48="","",IF(F48=0,0,F48*Catálogos!$R$1)) -> 357.89312 | K48: =IF(B48="","",IF(Catálogos!$K$10=1,Carátula!$F$17*Catálogos!$R$4,0)) -> 199.92 | L48: =IF(B48="","",IF(F48=0,0,CAT!H11)) -> 299 | N48: =IF(B48="","",IF(M48>0,M48-(M48/(1+Catálogos!$N$10)),0)) -> 0 | O48: =IF(B48="","",G48+H48+I48+J48+K48+L48) -> 6360.5722 | P48: =IF(B48="","",F48-G48) -> 595593.64 | Q48: =IF(OR(B48="",F48=0),"",1) -> 1
B49: =IF(B48=$H$29,"",IF(B48="","",B48+1)) -> 6 | C49: =IF(B49="","",'Fecha Pago'!K9) -> 46145 | D49: =IF(B49="","",'Fecha Pago'!L9) -> 30.4 | E49: =IF(B49="","",$E$39) -> 0.0915 | F49: =IF(B49="","",P48) -> 595593.64 | G49: =IF(B49="","",IF(F49=0,0,MIN(F49,IF(Catálogos!$N$6=1,Prepagos!C8,IF(Catálogos!$N$6=2,Prepagos!D8,IF(Catálogos!$N$6=3,Prepagos!E8,)))))) -> 901.80555 | H49: =IF(B49="","",IF(F49=0,0,(E49/360*D49)*F49)) -> 4601.9535 | I49: =IF(B49="","",IF($I$43<>"",H49*0.16,0)) -> 0 | J49: =IF(B49="","",IF(F49=0,0,F49*Catálogos!$R$1)) -> 357.35618 | K49: =IF(B49="","",IF(Catálogos!$K$10=1,Carátula!$F$17*Catálogos!$R$4,0)) -> 199.92 | L49: =IF(B49="","",IF(F49=0,0,CAT!H12)) -> 299 | N49: =IF(B49="","",IF(M49>0,M49-(M49/(1+Catálogos!$N$10)),0)) -> 0 | O49: =IF(B49="","",G49+H49+I49+J49+K49+L49) -> 6360.0352 | P49: =IF(B49="","",F49-G49) -> 594691.83 | Q49: =IF(OR(B49="",F49=0),"",1) -> 1
B50: =IF(B49=$H$29,"",IF(B49="","",B49+1)) -> 7 | C50: =IF(B50="","",'Fecha Pago'!K10) -> 46176 | D50: =IF(B50="","",'Fecha Pago'!L10) -> 30.4 | E50: =IF(B50="","",$E$39) -> 0.0915 | F50: =IF(B50="","",P49) -> 594691.83 | G50: =IF(B50="","",IF(F50=0,0,MIN(F50,IF(Catálogos!$N$6=1,Prepagos!C9,IF(Catálogos!$N$6=2,Prepagos!D9,IF(Catálogos!$N$6=3,Prepagos!E9,)))))) -> 908.7735 | H50: =IF(B50="","",IF(F50=0,0,(E50/360*D50)*F50)) -> 4594.9855 | I50: =IF(B50="","",IF($I$43<>"",H50*0.16,0)) -> 0 | J50: =IF(B50="","",IF(F50=0,0,F50*Catálogos!$R$1)) -> 356.8151 | K50: =IF(B50="","",IF(Catálogos!$K$10=1,Carátula!$F$17*Catálogos!$R$4,0)) -> 199.92 | L50: =IF(B50="","",IF(F50=0,0,CAT!H13)) -> 299 | N50: =IF(B50="","",IF(M50>0,M50-(M50/(1+Catálogos!$N$10)),0)) -> 0 | O50: =IF(B50="","",G50+H50+I50+J50+K50+L50) -> 6359.4941 | P50: =IF(B50="","",F50-G50) -> 593783.06 | Q50: =IF(OR(B50="",F50=0),"",1) -> 1
B51: =IF(B50=$H$29,"",IF(B50="","",B50+1)) -> 8 | C51: =IF(B51="","",'Fecha Pago'!K11) -> 46206 | D51: =IF(B51="","",'Fecha Pago'!L11) -> 30.4 | E51: =IF(B51="","",$E$39) -> 0.0915 | F51: =IF(B51="","",P50) -> 593783.06 | G51: =IF(B51="","",IF(F51=0,0,MIN(F51,IF(Catálogos!$N$6=1,Prepagos!C10,IF(Catálogos!$N$6=2,Prepagos!D10,IF(Catálogos!$N$6=3,Prepagos!E10,)))))) -> 915.79529 | H51: =IF(B51="","",IF(F51=0,0,(E51/360*D51)*F51)) -> 4587.9638 | I51: =IF(B51="","",IF($I$43<>"",H51*0.16,0)) -> 0 | J51: =IF(B51="","",IF(F51=0,0,F51*Catálogos!$R$1)) -> 356.26983 | K51: =IF(B51="","",IF(Catálogos!$K$10=1,Carátula!$F$17*Catálogos!$R$4,0)) -> 199.92 | L51: =IF(B51="","",IF(F51=0,0,CAT!H14)) -> 299 | N51: =IF(B51="","",IF(M51>0,M51-(M51/(1+Catálogos!$N$10)),0)) -> 0 | O51: =IF(B51="","",G51+H51+I51+J51+K51+L51) -> 6358.9489 | P51: =IF(B51="","",F51-G51) -> 592867.26 | Q51: =IF(OR(B51="",F51=0),"",1) -> 1
B52: =IF(B51=$H$29,"",IF(B51="","",B51+1)) -> 9 | C52: =IF(B52="","",'Fecha Pago'!K12) -> 46237 | D52: =IF(B52="","",'Fecha Pago'!L12) -> 30.4 | E52: =IF(B52="","",$E$39) -> 0.0915 | F52: =IF(B52="","",P51) -> 592867.26 | G52: =IF(B52="","",IF(F52=0,0,MIN(F52,IF(Catálogos!$N$6=1,Prepagos!C11,IF(Catálogos!$N$6=2,Prepagos!D11,IF(Catálogos!$N$6=3,Prepagos!E11,)))))) -> 922.87133 | H52: =IF(B52="","",IF(F52=0,0,(E52/360*D52)*F52)) -> 4580.8877 | I52: =IF(B52="","",IF($I$43<>"",H52*0.16,0)) -> 0 | J52: =IF(B52="","",IF(F52=0,0,F52*Catálogos!$R$1)) -> 355.72036 | K52: =IF(B52="","",IF(Catálogos!$K$10=1,Carátula!$F$17*Catálogos!$R$4,0)) -> 199.92 | L52: =IF(B52="","",IF(F52=0,0,CAT!H15)) -> 299 | N52: =IF(B52="","",IF(M52>0,M52-(M52/(1+Catálogos!$N$10)),0)) -> 0 | O52: =IF(B52="","",G52+H52+I52+J52+K52+L52) -> 6358.3994 | P52: =IF(B52="","",F52-G52) -> 591944.39 | Q52: =IF(OR(B52="",F52=0),"",1) -> 1
B53: =IF(B52=$H$29,"",IF(B52="","",B52+1)) -> 10 | C53: =IF(B53="","",'Fecha Pago'!K13) -> 46268 | D53: =IF(B53="","",'Fecha Pago'!L13) -> 30.4 | E53: =IF(B53="","",$E$39) -> 0.0915 | F53: =IF(B53="","",P52) -> 591944.39 | G53: =IF(B53="","",IF(F53=0,0,MIN(F53,IF(Catálogos!$N$6=1,Prepagos!C12,IF(Catálogos!$N$6=2,Prepagos!D12,IF(Catálogos!$N$6=3,Prepagos!E12,)))))) -> 930.00205 | H53: =IF(B53="","",IF(F53=0,0,(E53/360*D53)*F53)) -> 4573.757 | I53: =IF(B53="","",IF($I$43<>"",H53*0.16,0)) -> 0 | J53: =IF(B53="","",IF(F53=0,0,F53*Catálogos!$R$1)) -> 355.16663 | K53: =IF(B53="","",IF(Catálogos!$K$10=1,Carátula!$F$17*Catálogos!$R$4,0)) -> 199.92 | L53: =IF(B53="","",IF(F53=0,0,CAT!H16)) -> 299 | N53: =IF(B53="","",IF(M53>0,M53-(M53/(1+Catálogos!$N$10)),0)) -> 0 | O53: =IF(B53="","",G53+H53+I53+J53+K53+L53) -> 6357.8457 | P53: =IF(B53="","",F53-G53) -> 591014.39 | Q53: =IF(OR(B53="",F53=0),"",1) -> 1
B54: =IF(B53=$H$29,"",IF(B53="","",B53+1)) -> 11 | C54: =IF(B54="","",'Fecha Pago'!K14) -> 46298 | D54: =IF(B54="","",'Fecha Pago'!L14) -> 30.4 | E54: =IF(B54="","",$E$39) -> 0.0915 | F54: =IF(B54="","",P53) -> 591014.39 | G54: =IF(B54="","",IF(F54=0,0,MIN(F54,IF(Catálogos!$N$6=1,Prepagos!C13,IF(Catálogos!$N$6=2,Prepagos!D13,IF(Catálogos!$N$6=3,Prepagos!E13,)))))) -> 937.18787 | H54: =IF(B54="","",IF(F54=0,0,(E54/360*D54)*F54)) -> 4566.5712 | I54: =IF(B54="","",IF($I$43<>"",H54*0.16,0)) -> 0 | J54: =IF(B54="","",IF(F54=0,0,F54*Catálogos!$R$1)) -> 354.60863 | K54: =IF(B54="","",IF(Catálogos!$K$10=1,Carátula!$F$17*Catálogos!$R$4,0)) -> 199.92 | L54: =IF(B54="","",IF(F54=0,0,CAT!H17)) -> 299 | N54: =IF(B54="","",IF(M54>0,M54-(M54/(1+Catálogos!$N$10)),0)) -> 0 | O54: =IF(B54="","",G54+H54+I54+J54+K54+L54) -> 6357.2877 | P54: =IF(B54="","",F54-G54) -> 590077.2 | Q54: =IF(OR(B54="",F54=0),"",1) -> 1
B55: =IF(B54=$H$29,"",IF(B54="","",B54+1)) -> 12 | C55: =IF(B55="","",'Fecha Pago'!K15) -> 46329 | D55: =IF(B55="","",'Fecha Pago'!L15) -> 30.4 | E55: =IF(B55="","",$E$39) -> 0.0915 | F55: =IF(B55="","",P54) -> 590077.2 | G55: =IF(B55="","",IF(F55=0,0,MIN(F55,IF(Catálogos!$N$6=1,Prepagos!C14,IF(Catálogos!$N$6=2,Prepagos!D14,IF(Catálogos!$N$6=3,Prepagos!E14,)))))) -> 944.42921 | H55: =IF(B55="","",IF(F55=0,0,(E55/360*D55)*F55)) -> 4559.3298 | I55: =IF(B55="","",IF($I$43<>"",H55*0.16,0)) -> 0 | J55: =IF(B55="","",IF(F55=0,0,F55*Catálogos!$R$1)) -> 354.04632 | K55: =IF(B55="","",IF(Catálogos!$K$10=1,Carátula!$F$17*Catálogos!$R$4,0)) -> 199.92 | L55: =IF(B55="","",IF(F55=0,0,CAT!H18)) -> 299 | N55: =IF(B55="","",IF(M55>0,M55-(M55/(1+Catálogos!$N$10)),0)) -> 0 | O55: =IF(B55="","",G55+H55+I55+J55+K55+L55) -> 6356.7254 | P55: =IF(B55="","",F55-G55) -> 589132.77 | Q55: =IF(OR(B55="",F55=0),"",1) -> 1
B56: =IF(B55=$H$29,"",IF(B55="","",B55+1)) -> 13 | C56: =IF(B56="","",'Fecha Pago'!K16) -> 46359 | D56: =IF(B56="","",'Fecha Pago'!L16) -> 30.4 | E56: =IF(B56="","",$E$39) -> 0.0915 | F56: =IF(B56="","",P55) -> 589132.77 | G56: =IF(B56="","",IF(F56=0,0,MIN(F56,IF(Catálogos!$N$6=1,Prepagos!C15,IF(Catálogos!$N$6=2,Prepagos!D15,IF(Catálogos!$N$6=3,Prepagos!E15,)))))) -> 951.7265 | H56: =IF(B56="","",IF(F56=0,0,(E56/360*D56)*F56)) -> 4552.0325 | I56: =IF(B56="","",IF($I$43<>"",H56*0.16,0)) -> 0 | J56: =IF(B56="","",IF(F56=0,0,F56*Catálogos!$R$1)) -> 353.47966 | K56: =IF(B56="","",IF(Catálogos!$K$10=1,Carátula!$F$17*Catálogos!$R$4,0)) -> 199.92 | L56: =IF(B56="","",IF(F56=0,0,CAT!H19)) -> 299 | N56: =IF(B56="","",IF(M56>0,M56-(M56/(1+Catálogos!$N$10)),0)) -> 0 | O56: =IF(B56="","",G56+H56+I56+J56+K56+L56) -> 6356.1587 | P56: =IF(B56="","",F56-G56) -> 588181.04 | Q56: =IF(OR(B56="",F56=0),"",1) -> 1
... B79: =IF(B78=$H$29,"",IF(B78="","",B78+1)) -> 36 | C79: =IF(B79="","",'Fecha Pago'!K39) -> 47060 | D79: =IF(B79="","",'Fecha Pago'!L39) -> 30.4 | E79: =IF(B79="","",$E$39) -> 0.0915 | F79: =IF(B79="","",P78) -> 565277.95 | G79: =IF(B79="","",IF(F79=0,0,MIN(F79,IF(Catálogos!$N$6=1,Prepagos!C38,IF(Catálogos!$N$6=2,Prepagos!D38,IF(Catálogos!$N$6=3,Prepagos!E38,)))))) -> 1136.0447 | H79: =IF(B79="","",IF(F79=0,0,(E79/360*D79)*F79)) -> 4367.7143 | I79: =IF(B79="","",IF($I$43<>"",H79*0.16,0)) -> 0 | J79: =IF(B79="","",IF(F79=0,0,F79*Catálogos!$R$1)) -> 339.16677 | K79: =IF(B79="","",IF(Catálogos!$K$10=1,Carátula!$F$17*Catálogos!$R$4,0)) -> 199.92 | L79: =IF(B79="","",IF(F79=0,0,CAT!H42)) -> 299 | N79: =IF(B79="","",IF(M79>0,M79-(M79/(1+Catálogos!$N$10)),0)) -> 0 | O79: =IF(B79="","",G79+H79+I79+J79+K79+L79) -> 6341.8458 | P79: =IF(B79="","",F79-G79) -> 564141.91 | Q79: =IF(OR(B79="",F79=0),"",1) -> 1
B80: =IF(B79=$H$29,"",IF(B79="","",B79+1)) -> 37 | C80: =IF(B80="","",'Fecha Pago'!K40) -> 47090 | D80: =IF(B80="","",'Fecha Pago'!L40) -> 30.4 | E80: =IF(B80="","",$E$39) -> 0.0915 | F80: =IF(B80="","",P79) -> 564141.91 | G80: =IF(B80="","",IF(F80=0,0,MIN(F80,IF(Catálogos!$N$6=1,Prepagos!C39,IF(Catálogos!$N$6=2,Prepagos!D39,IF(Catálogos!$N$6=3,Prepagos!E39,)))))) -> 1144.8226 | H80: =IF(B80="","",IF(F80=0,0,(E80/360*D80)*F80)) -> 4358.9365 | I80: =IF(B80="","",IF($I$43<>"",H80*0.16,0)) -> 0 | J80: =IF(B80="","",IF(F80=0,0,F80*Catálogos!$R$1)) -> 338.48514 | K80: =IF(B80="","",IF(Catálogos!$K$10=1,Carátula!$F$17*Catálogos!$R$4,0)) -> 199.92 | L80: =IF(B80="","",IF(F80=0,0,CAT!H43)) -> 299 | N80: =IF(B80="","",0) -> 0 | O80: =IF(B80="","",G80+H80+I80+J80+K80+L80) -> 6341.1642 | P80: =IF(B80="","",F80-G80) -> 562997.08 | Q80: =IF(OR(B80="",F80=0),"",1) -> 1
B81: =IF(B80=$H$29,"",IF(B80="","",B80+1)) -> 38 | C81: =IF(B81="","",'Fecha Pago'!K41) -> 47121 | D81: =IF(B81="","",'Fecha Pago'!L41) -> 30.4 | E81: =IF(B81="","",$E$39) -> 0.0915 | F81: =IF(B81="","",P80) -> 562997.08 | G81: =IF(B81="","",IF(F81=0,0,MIN(F81,IF(Catálogos!$N$6=1,Prepagos!C40,IF(Catálogos!$N$6=2,Prepagos!D40,IF(Catálogos!$N$6=3,Prepagos!E40,)))))) -> 1153.6682 | H81: =IF(B81="","",IF(F81=0,0,(E81/360*D81)*F81)) -> 4350.0908 | I81: =IF(B81="","",IF($I$43<>"",H81*0.16,0)) -> 0 | J81: =IF(B81="","",IF(F81=0,0,F81*Catálogos!$R$1)) -> 337.79825 | K81: =IF(B81="","",IF(Catálogos!$K$10=1,Carátula!$F$17*Catálogos!$R$4,0)) -> 199.92 | L81: =IF(B81="","",IF(F81=0,0,CAT!H44)) -> 299 | N81: =IF(B81="","",0) -> 0 | O81: =IF(B81="","",G81+H81+I81+J81+K81+L81) -> 6340.4773 | P81: =IF(B81="","",F81-G81) -> 561843.42 | Q81: =IF(OR(B81="",F81=0),"",1) -> 1
B82: =IF(B81=$H$29,"",IF(B81="","",B81+1)) -> 39 | C82: =IF(B82="","",'Fecha Pago'!K42) -> 47152 | D82: =IF(B82="","",'Fecha Pago'!L42) -> 30.4 | E82: =IF(B82="","",$E$39) -> 0.0915 | F82: =IF(B82="","",P81) -> 561843.42 | G82: =IF(B82="","",IF(F82=0,0,MIN(F82,IF(Catálogos!$N$6=1,Prepagos!C41,IF(Catálogos!$N$6=2,Prepagos!D41,IF(Catálogos!$N$6=3,Prepagos!E41,)))))) -> 1162.5823 | H82: =IF(B82="","",IF(F82=0,0,(E82/360*D82)*F82)) -> 4341.1768 | I82: =IF(B82="","",IF($I$43<>"",H82*0.16,0)) -> 0 | J82: =IF(B82="","",IF(F82=0,0,F82*Catálogos!$R$1)) -> 337.10605 | K82: =IF(B82="","",IF(Catálogos!$K$10=1,Carátula!$F$17*Catálogos!$R$4,0)) -> 199.92 | L82: =IF(B82="","",IF(F82=0,0,CAT!H45)) -> 299 | N82: =IF(B82="","",0) -> 0 | O82: =IF(B82="","",G82+H82+I82+J82+K82+L82) -> 6339.7851 | P82: =IF(B82="","",F82-G82) -> 560680.83 | Q82: =IF(OR(B82="",F82=0),"",1) -> 1
B83: =IF(B82=$H$29,"",IF(B82="","",B82+1)) -> 40 | C83: =IF(B83="","",'Fecha Pago'!K43) -> 47180 | D83: =IF(B83="","",'Fecha Pago'!L43) -> 30.4 | E83: =IF(B83="","",$E$39) -> 0.0915 | F83: =IF(B83="","",P82) -> 560680.83 | G83: =IF(B83="","",IF(F83=0,0,MIN(F83,IF(Catálogos!$N$6=1,Prepagos!C42,IF(Catálogos!$N$6=2,Prepagos!D42,IF(Catálogos!$N$6=3,Prepagos!E42,)))))) -> 1171.5651 | H83: =IF(B83="","",IF(F83=0,0,(E83/360*D83)*F83)) -> 4332.1939 | I83: =IF(B83="","",IF($I$43<>"",H83*0.16,0)) -> 0 | J83: =IF(B83="","",IF(F83=0,0,F83*Catálogos!$R$1)) -> 336.4085 | K83: =IF(B83="","",IF(Catálogos!$K$10=1,Carátula!$F$17*Catálogos!$R$4,0)) -> 199.92 | L83: =IF(B83="","",IF(F83=0,0,CAT!H46)) -> 299 | N83: =IF(B83="","",0) -> 0 | O83: =IF(B83="","",G83+H83+I83+J83+K83+L83) -> 6339.0875 | P83: =IF(B83="","",F83-G83) -> 559509.27 | Q83: =IF(OR(B83="",F83=0),"",1) -> 1
B84: =IF(B83=$H$29,"",IF(B83="","",B83+1)) -> 41 | C84: =IF(B84="","",'Fecha Pago'!K44) -> 47211 | D84: =IF(B84="","",'Fecha Pago'!L44) -> 30.4 | E84: =IF(B84="","",$E$39) -> 0.0915 | F84: =IF(B84="","",P83) -> 559509.27 | G84: =IF(B84="","",IF(F84=0,0,MIN(F84,IF(Catálogos!$N$6=1,Prepagos!C43,IF(Catálogos!$N$6=2,Prepagos!D43,IF(Catálogos!$N$6=3,Prepagos!E43,)))))) -> 1180.6174 | H84: =IF(B84="","",IF(F84=0,0,(E84/360*D84)*F84)) -> 4323.1416 | I84: =IF(B84="","",IF($I$43<>"",H84*0.16,0)) -> 0 | J84: =IF(B84="","",IF(F84=0,0,F84*Catálogos!$R$1)) -> 335.70556 | K84: =IF(B84="","",IF(Catálogos!$K$10=1,Carátula!$F$17*Catálogos!$R$4,0)) -> 199.92 | L84: =IF(B84="","",IF(F84=0,0,CAT!H47)) -> 299 | N84: =IF(B84="","",0) -> 0 | O84: =IF(B84="","",G84+H84+I84+J84+K84+L84) -> 6338.3846 | P84: =IF(B84="","",F84-G84) -> 558328.65 | Q84: =IF(OR(B84="",F84=0),"",1) -> 1
B85: =IF(B84=$H$29,"",IF(B84="","",B84+1)) -> 42 | C85: =IF(B85="","",'Fecha Pago'!K45) -> 47241 | D85: =IF(B85="","",'Fecha Pago'!L45) -> 30.4 | E85: =IF(B85="","",$E$39) -> 0.0915 | F85: =IF(B85="","",P84) -> 558328.65 | G85: =IF(B85="","",IF(F85=0,0,MIN(F85,IF(Catálogos!$N$6=1,Prepagos!C44,IF(Catálogos!$N$6=2,Prepagos!D44,IF(Catálogos!$N$6=3,Prepagos!E44,)))))) -> 1189.7397 | H85: =IF(B85="","",IF(F85=0,0,(E85/360*D85)*F85)) -> 4314.0194 | I85: =IF(B85="","",IF($I$43<>"",H85*0.16,0)) -> 0 | J85: =IF(B85="","",IF(F85=0,0,F85*Catálogos!$R$1)) -> 334.99719 | K85: =IF(B85="","",IF(Catálogos!$K$10=1,Carátula!$F$17*Catálogos!$R$4,0)) -> 199.92 | L85: =IF(B85="","",IF(F85=0,0,CAT!H48)) -> 299 | N85: =IF(B85="","",0) -> 0 | O85: =IF(B85="","",G85+H85+I85+J85+K85+L85) -> 6337.6762 | P85: =IF(B85="","",F85-G85) -> 557138.91 | Q85: =IF(OR(B85="",F85=0),"",1) -> 1
B86: =IF(B85=$H$29,"",IF(B85="","",B85+1)) -> 43 | C86: =IF(B86="","",'Fecha Pago'!K46) -> 47272 | D86: =IF(B86="","",'Fecha Pago'!L46) -> 30.4 | E86: =IF(B86="","",$E$39) -> 0.0915 | F86: =IF(B86="","",P85) -> 557138.91 | G86: =IF(B86="","",IF(F86=0,0,MIN(F86,IF(Catálogos!$N$6=1,Prepagos!C45,IF(Catálogos!$N$6=2,Prepagos!D45,IF(Catálogos!$N$6=3,Prepagos!E45,)))))) -> 1198.9324 | H86: =IF(B86="","",IF(F86=0,0,(E86/360*D86)*F86)) -> 4304.8266 | I86: =IF(B86="","",IF($I$43<>"",H86*0.16,0)) -> 0 | J86: =IF(B86="","",IF(F86=0,0,F86*Catálogos!$R$1)) -> 334.28335 | K86: =IF(B86="","",IF(Catálogos!$K$10=1,Carátula!$F$17*Catálogos!$R$4,0)) -> 199.92 | L86: =IF(B86="","",IF(F86=0,0,CAT!H49)) -> 299 | N86: =IF(B86="","",0) -> 0 | O86: =IF(B86="","",G86+H86+I86+J86+K86+L86) -> 6336.9624 | P86: =IF(B86="","",F86-G86) -> 555939.98 | Q86: =IF(OR(B86="",F86=0),"",1) -> 1
B87: =IF(B86=$H$29,"",IF(B86="","",B86+1)) -> 44 | C87: =IF(B87="","",'Fecha Pago'!K47) -> 47302 | D87: =IF(B87="","",'Fecha Pago'!L47) -> 30.4 | E87: =IF(B87="","",$E$39) -> 0.0915 | F87: =IF(B87="","",P86) -> 555939.98 | G87: =IF(B87="","",IF(F87=0,0,MIN(F87,IF(Catálogos!$N$6=1,Prepagos!C46,IF(Catálogos!$N$6=2,Prepagos!D46,IF(Catálogos!$N$6=3,Prepagos!E46,)))))) -> 1208.1961 | H87: =IF(B87="","",IF(F87=0,0,(E87/360*D87)*F87)) -> 4295.5629 | I87: =IF(B87="","",IF($I$43<>"",H87*0.16,0)) -> 0 | J87: =IF(B87="","",IF(F87=0,0,F87*Catálogos!$R$1)) -> 333.56399 | K87: =IF(B87="","",IF(Catálogos!$K$10=1,Carátula!$F$17*Catálogos!$R$4,0)) -> 199.92 | L87: =IF(B87="","",IF(F87=0,0,CAT!H50)) -> 299 | N87: =IF(B87="","",0) -> 0 | O87: =IF(B87="","",G87+H87+I87+J87+K87+L87) -> 6336.243 | P87: =IF(B87="","",F87-G87) -> 554731.78 | Q87: =IF(OR(B87="",F87=0),"",1) -> 1
B88: =IF(B87=$H$29,"",IF(B87="","",B87+1)) -> 45 | C88: =IF(B88="","",'Fecha Pago'!K48) -> 47333 | D88: =IF(B88="","",'Fecha Pago'!L48) -> 30.4 | E88: =IF(B88="","",$E$39) -> 0.0915 | F88: =IF(B88="","",P87) -> 554731.78 | G88: =IF(B88="","",IF(F88=0,0,MIN(F88,IF(Catálogos!$N$6=1,Prepagos!C47,IF(Catálogos!$N$6=2,Prepagos!D47,IF(Catálogos!$N$6=3,Prepagos!E47,)))))) -> 1217.5315 | H88: =IF(B88="","",IF(F88=0,0,(E88/360*D88)*F88)) -> 4286.2276 | I88: =IF(B88="","",IF($I$43<>"",H88*0.16,0)) -> 0 | J88: =IF(B88="","",IF(F88=0,0,F88*Catálogos!$R$1)) -> 332.83907 | K88: =IF(B88="","",IF(Catálogos!$K$10=1,Carátula!$F$17*Catálogos!$R$4,0)) -> 199.92 | L88: =IF(B88="","",IF(F88=0,0,CAT!H51)) -> 299 | N88: =IF(B88="","",0) -> 0 | O88: =IF(B88="","",G88+H88+I88+J88+K88+L88) -> 6335.5181 | P88: =IF(B88="","",F88-G88) -> 553514.25 | Q88: =IF(OR(B88="",F88=0),"",1) -> 1
B89: =IF(B88=$H$29,"",IF(B88="","",B88+1)) -> 46 | C89: =IF(B89="","",'Fecha Pago'!K49) -> 47364 | D89: =IF(B89="","",'Fecha Pago'!L49) -> 30.4 | E89: =IF(B89="","",$E$39) -> 0.0915 | F89: =IF(B89="","",P88) -> 553514.25 | G89: =IF(B89="","",IF(F89=0,0,MIN(F89,IF(Catálogos!$N$6=1,Prepagos!C48,IF(Catálogos!$N$6=2,Prepagos!D48,IF(Catálogos!$N$6=3,Prepagos!E48,)))))) -> 1226.9389 | H89: =IF(B89="","",IF(F89=0,0,(E89/360*D89)*F89)) -> 4276.8201 | I89: =IF(B89="","",IF($I$43<>"",H89*0.16,0)) -> 0 | J89: =IF(B89="","",IF(F89=0,0,F89*Catálogos!$R$1)) -> 332.10855 | K89: =IF(B89="","",IF(Catálogos!$K$10=1,Carátula!$F$17*Catálogos!$R$4,0)) -> 199.92 | L89: =IF(B89="","",IF(F89=0,0,CAT!H52)) -> 299 | N89: =IF(B89="","",0) -> 0 | O89: =IF(B89="","",G89+H89+I89+J89+K89+L89) -> 6334.7876 | P89: =IF(B89="","",F89-G89) -> 552287.31 | Q89: =IF(OR(B89="",F89=0),"",1) -> 1
B90: =IF(B89=$H$29,"",IF(B89="","",B89+1)) -> 47 | C90: =IF(B90="","",'Fecha Pago'!K50) -> 47394 | D90: =IF(B90="","",'Fecha Pago'!L50) -> 30.4 | E90: =IF(B90="","",$E$39) -> 0.0915 | F90: =IF(B90="","",P89) -> 552287.31 | G90: =IF(B90="","",IF(F90=0,0,MIN(F90,IF(Catálogos!$N$6=1,Prepagos!C49,IF(Catálogos!$N$6=2,Prepagos!D49,IF(Catálogos!$N$6=3,Prepagos!E49,)))))) -> 1236.4191 | H90: =IF(B90="","",IF(F90=0,0,(E90/360*D90)*F90)) -> 4267.34 | I90: =IF(B90="","",IF($I$43<>"",H90*0.16,0)) -> 0 | J90: =IF(B90="","",IF(F90=0,0,F90*Catálogos!$R$1)) -> 331.37239 | K90: =IF(B90="","",IF(Catálogos!$K$10=1,Carátula!$F$17*Catálogos!$R$4,0)) -> 199.92 | L90: =IF(B90="","",IF(F90=0,0,CAT!H53)) -> 299 | N90: =IF(B90="","",0) -> 0 | O90: =IF(B90="","",G90+H90+I90+J90+K90+L90) -> 6334.0514 | P90: =IF(B90="","",F90-G90) -> 551050.89 | Q90: =IF(OR(B90="",F90=0),"",1) -> 1
B91: =IF(B90=$H$29,"",IF(B90="","",B90+1)) -> 48 | C91: =IF(B91="","",'Fecha Pago'!K51) -> 47425 | D91: =IF(B91="","",'Fecha Pago'!L51) -> 30.4 | E91: =IF(B91="","",$E$39) -> 0.0915 | F91: =IF(B91="","",P90) -> 551050.89 | G91: =IF(B91="","",IF(F91=0,0,MIN(F91,IF(Catálogos!$N$6=1,Prepagos!C50,IF(Catálogos!$N$6=2,Prepagos!D50,IF(Catálogos!$N$6=3,Prepagos!E50,)))))) -> 1245.9725 | H91: =IF(B91="","",IF(F91=0,0,(E91/360*D91)*F91)) -> 4257.7866 | I91: =IF(B91="","",IF($I$43<>"",H91*0.16,0)) -> 0 | J91: =IF(B91="","",IF(F91=0,0,F91*Catálogos!$R$1)) -> 330.63054 | K91: =IF(B91="","",IF(Catálogos!$K$10=1,Carátula!$F$17*Catálogos!$R$4,0)) -> 199.92 | L91: =IF(B91="","",IF(F91=0,0,CAT!H54)) -> 299 | N91: =IF(B91="","",0) -> 0 | O91: =IF(B91="","",G91+H91+I91+J91+K91+L91) -> 6333.3096 | P91: =IF(B91="","",F91-G91) -> 549804.92 | Q91: =IF(OR(B91="",F91=0),"",1) -> 1
... B283: =IF(B282=$H$29,"",IF(B282="","",B282+1)) -> 240 | C283: =IF(B283="","",'Fecha Pago'!K243) -> 53269 | D283: =IF(B283="","",'Fecha Pago'!L243) -> 30.4 | E283: =IF(B283="","",$E$39) -> 0.0915 | F283: =IF(B283="","",P282) -> 5461.5594 | G283: =IF(B283="","",IF(F283=0,0,MIN(F283,IF(Catálogos!$N$6=1,Prepagos!C242,IF(Catálogos!$N$6=2,Prepagos!D242,IF(Catálogos!$N$6=3,Prepagos!E242,)))))) -> 5461.5594 | H283: =IF(B283="","",IF(F283=0,0,(E283/360*D283)*F283)) -> 42.199649 | I283: =IF(B283="","",IF($I$43<>"",H283*0.16,0)) -> 0 | J283: =IF(B283="","",IF(F283=0,0,F283*Catálogos!$R$1)) -> 3.2769356 | K283: =IF(B283="","",IF(Catálogos!$K$10=1,Carátula!$F$17*Catálogos!$R$4,0)) -> 199.92 | L283: =IF(B283="","",IF(F283=0,0,CAT!H246)) -> 299 | N283: =IF(B283="","",0) -> 0 | O283: =IF(B283="","",G283+H283+I283+J283+K283+L283) -> 6005.956 | P283: =IF(B283="","",F283-G283) -> 2.3283064e-10 | Q283: =IF(OR(B283="",F283=0),"",1) -> 1
B285: Totales | G285: =SUM(G44:G283) -> 600000 | H285: =SUM(H44:H283) -> 719621.17 | I285: =SUM(I44:I283) -> 0 | J285: =SUM(J44:J283) -> 55884.324 | K285: =SUM(K44:K283) -> 47927.488 | L285: =SUM(L44:L283) -> 71760 | O285: =SUM(O44:O283) -> 1495193
B287: La presente información es únicamente para efectos ilustrativos, no representa ningún ofrecimiento formal por parte de Grupo Financiero Banorte. El CAT es para fines informativos y de comparación exclusivamente.

Sheet Tabla Notaría
B4: Cliente: | C4: =Carátula!L2 -> 0
B5: Esquema: | C5: Crédito Hipotecario | D5: Tasa fija con amortización creciente
B6: Tasa de Interés Anual (Fija): | C6: =Carátula!$E$39 -> 0.0915
B7: Monto Total de Crédito: | C7: =Carátula!$F$44 -> 600000
B8: Destino del Crédito: | C8: =Carátula!I35 -> Mejora de Hipoteca
B10: Tabla de amortización en pesos
B11: No. | C11: Saldo | D11: Amortización a Capital | E11: Saldo Nuevo
B12: 1 | C12: =CAT!B7 -> 600000 | D12: =CAT!C7 -> 867.75904 | E12: =IF(B12="","",C12-D12) -> 599132.24
B13: =CAT!A8 -> 2 | C13: =CAT!B8 -> 599132.24 | D13: =CAT!C8 -> 874.46393 | E13: =IF(B13="","",C13-D13) -> 598257.78
B14: =CAT!A9 -> 3 | C14: =CAT!B9 -> 598257.78 | D14: =CAT!C9 -> 881.22062 | E14: =IF(B14="","",C14-D14) -> 597376.56
B15: =CAT!A10 -> 4 | C15: =CAT!B10 -> 597376.56 | D15: =CAT!C10 -> 888.02952 | E15: =IF(B15="","",C15-D15) -> 596488.53
B16: =CAT!A11 -> 5 | C16: =CAT!B11 -> 596488.53 | D16: =CAT!C11 -> 894.89102 | E16: =IF(B16="","",C16-D16) -> 595593.64
B17: =CAT!A12 -> 6 | C17: =CAT!B12 -> 595593.64 | D17: =CAT!C12 -> 901.80555 | E17: =IF(B17="","",C17-D17) -> 594691.83
B18: =CAT!A13 -> 7 | C18: =CAT!B13 -> 594691.83 | D18: =CAT!C13 -> 908.7735 | E18: =IF(B18="","",C18-D18) -> 593783.06
B19: =CAT!A14 -> 8 | C19: =CAT!B14 -> 593783.06 | D19: =CAT!C14 -> 915.79529 | E19: =IF(B19="","",C19-D19) -> 592867.26
B20: =CAT!A15 -> 9 | C20: =CAT!B15 -> 592867.26 | D20: =CAT!C15 -> 922.87133 | E20: =IF(B20="","",C20-D20) -> 591944.39
B21: =CAT!A16 -> 10 | C21: =CAT!B16 -> 591944.39 | D21: =CAT!C16 -> 930.00205 | E21: =IF(B21="","",C21-D21) -> 591014.39
B22: =CAT!A17 -> 11 | C22: =CAT!B17 -> 591014.39 | D22: =CAT!C17 -> 937.18787 | E22: =IF(B22="","",C22-D22) -> 590077.2
B23: =CAT!A18 -> 12 | C23: =CAT!B18 -> 590077.2 | D23: =CAT!C18 -> 944.42921 | E23: =IF(B23="","",C23-D23) -> 589132.77
B24: =CAT!A19 -> 13 | C24: =CAT!B19 -> 589132.77 | D24: =CAT!C19 -> 951.7265 | E24: =IF(B24="","",C24-D24) -> 588181.04
... B251: =CAT!A246 -> 240 | C251: =CAT!B246 -> 5461.5594 | D251: =CAT!C246 -> 5461.5594 | E251: =IF(B251="","",C251-D251) -> 1.1223165e-09

Sheet Oferta Vinculante
A2: Banco Mercantil del Norte, S.A. Institución de Banca Múltiple, Grupo Financiero Banorte
A3: Lugar y fecha de recepción de la Oferta Vinculante: | D3: monterrey | E3: =Carátula!F7 -> 45973
A5: La presente Oferta Vinculante establece los términos y condiciones específicos mediante los cuales El Banco se obliga a otorgar el Crédito a:
A6: Capturar nombre del cliente | D6: con R.F.C. | E6: Captura R.F.C. del Solicitante
A7: y domicilio en: | B7: Captura domicilio del Solicitante
A8: La vigencia de esta Oferta Vinculante es de 20 (veinte) días naturales contados a partir de su fecha de recepción, El Banco se obliga a otorgar el Crédito Garantizado a la Vivienda en los términos y condiciones que se indican, siempre y cuando dentro del plazo señalado el Solicitante dé aviso por escrito de la aceptación de la Oferta Vinculante y requisite toda la documentación soporte de la información que se haya declarado en la solicitud y El Banco compruebe: a) la identidad del Solicitante; b) la veracidad y autenticidad de los datos proporcionados en la Solicitud de Crédito; c) la capacidad crediticia conforme a las sanas prácticas bancarias y condiciones de mercado; d) la realización de un avalúo practicado por un valuador autorizado; y e) el cumplimiento de las demás formalidades que requiera la Ley.
A13: En caso de que el Solicitante incumpla con alguno de los requisitos supuestos o documentos señalados, la Oferta Vinculante queda sin efecto y El Banco no estará obligado en forma alguna a otorgar el crédito al Solicitante.
A15: Identificación del crédito | D15: Costo Anual Total (CAT)
A16: Esquema | B16: =Carátula!F13 -> Tradicional | D16: =Carátula!D41 -> 0.11779232 | E16: Sin I.V.A. | H16: =IF([1]Simulador!$F$9="Liquidez",[1]Simulador!$F$9,IF([1]Simulador!$F$9='[1]Tabla Parámetros'!$J$11,[1]Simulador!$F$9,'Oferta Vinculante'!$H$18)) -> Adquisición Hipoteca (Hipoteca Fuerte)
A17: Destino | B17: =Carátula!I35 -> Mejora de Hipoteca | H17: =[1]Simulador!$F$9 -> Adquisición | I17: Hipoteca | J17: =[1]Simulador!$F$11 -> Hipoteca Fuerte
A18: Importe Solicitado | B18: =Carátula!F44 -> 600000 | H18: =H17&" "&I17&"("&J17&")" -> Adquisición Hipoteca (Hipoteca Fuerte)
A19: Forma de entrega | B19: Depósito en cuenta.
A20: Descuentos o premios | B20: No Aplica
A21: El valor de la garantía | B21: =Carátula!F15 -> 1020000
A22: Aforo o % a financiar | B22: =IF(Carátula!I35="Liquidez",Carátula!N17,Carátula!N15) -> 0.58823529
H23: Tasa de Interés Anual Fija
A24: =H23&I24 -> Tasa de Interés Anual Fija | D24: Supuestos asumidos en el cálculo del CAT | I24: =IF([1]Simulador!$F$11='[1]Tabla Parámetros'!$O$4,"*"," ")
A25: Tipo | B25: Fija | D25: Cálculo de interés | E25: Sobre mes de 30.4 días | K25: 1.00%, no genera I.V.A.
A26: Ordinaria | B26: =Carátula!E39 -> 0.0915 | K26: =IF([1]Simulador!$F$9='[1]Tabla Parámetros'!$J$7,'Oferta Vinculante'!$K$25,IF([1]Simulador!$F$9='[1]Tabla Parámetros'!$J$8,'Oferta Vinculante'!$K$25,IF([1]Simulador!$F$9='[1]Tabla Parámetros'!$J$9,'Oferta Vinculante'!$K$25,"No Aplica"))) -> No Aplica
A27: Moratoria | B27: =$B$26*2 -> 0.183
K28: 1.00%, no genera I.V.A.
A29: Plazo / años | B29: =Carátula!H29/12 -> 20 | K29: =[1]Simulador!$N$15 -> 0.01
A31: Formas de amortización y revisión de tasas | D31: ="Componentes y valores " & VLOOKUP(2,NN.Catalogo,6) & " del CAT" -> #REF! | K31: Contratación - crédito | M31: =IF([1]Simulador!$N$17="SI","Financiada",IF([1]Simulador!$N$17="NO","Contado",)) -> Contado
A32: Amortización | B32: Mensual | D32: =$K$31&$M$31 -> Contratación - crédito Contado | K32: Gastos de Preoriginación - avalúo hipotecario
A33: Revisión de tasa variable | B33: No Aplica | D33: =K32&" "&M32 -> Gastos de Preoriginación - avalúo hipotecario | K33: Gastos de Preoriginación - gastos de aprobación
D34: Gastos de Preoriginación - gastos de aprobación | K34: Amortización a capital e Interés
A35: Comisiones aplicables | D35: Amortización a capital e Interés | K35: Seguro de Vida.
A36: =K31 -> Contratación - crédito | B36: 0 | D36: Seguro de Vida. | K36: Seguro de Daños y Contenidos.
A37: Penalización por pago anticipado de crédito | B37: No Aplica | D37: Seguro de Daños y Contenidos. | K37: Administración - autorización de crédito diferido
A38: Contratación - supervisión de uso de recursos | B38: =K26 -> No Aplica | D38: =K37 -> Administración - autorización de crédito diferido
A39: Gastos de Preoriginación - gastos de aprobación | B39: =Carátula!L30 -> 750 | D39: =[2]Cotización!$B$89 & VLOOKUP(3,NN.Catalogo,6) -> #REF! | E39: =Monto_Devolución -> #REF!
A40: Por autorización de crédito diferida | B40: =Carátula!L44 -> 299
D41: =IF(Mujer_Banorte="Sí","Servicio de Asistencias","") -> #REF! | L41: No genera I.V.A.
A42: Penalización por pago tardío | B42: 5.00% más I.V.A. | D42: =IF(Mujer_Banorte="Sí","Seguro de Enfermedades Graves y Momentos de Vida","") -> #REF!
A43: Contratación - crédito; sustitución del deudor | B43: 1.50% del saldo insoluto. Para saldos insolutos menores a $100,00.00 el importe es de $1,500.00 | D43: =IF(Destino=Construcción,"Comisión por supervisión de obra contado","") -> #REF!
A45: ="Seguros " & VLOOKUP(4,NN.Catalogo,6) -> #REF! | D45: Costos de servicios prestados | K45: Al millar más I.V.A.
A46: =[2]Tipo_Seguro!o.Leyenda_Vida -> Seguro de Vida, Enfermedades Graves y Momentos de Vida. | B46: ="$"&L47&K47 -> $360 No genera I.V.A. | D46: Avalúo hipotecario | E46: =K46 -> 2.5 Al millar más I.V.A. | H46: =Carátula!L28+Carátula!L29 -> 18431.034 | I46: (monto estimado en virtud de tratarse de cantidades determinadas por el Notario Público, Registro Público de la Propiedad respectivo, de acuerdo al monto de la operación). | K46: ='[1]Tabla Parámetros'!Q90&" "&" "&'Oferta Vinculante'!K45 -> 2.5 Al millar más I.V.A.
D47: Gastos, derechos y honorarios notariales | E47: =H46 -> 18431.034 | J47: =CAT!F7 -> 360 | K47: No genera I.V.A. | L47: =ROUNDUP(J47,2) -> 360
A48: =[2]Tipo_Seguro!o.Leyenda_OV_Seguros_Daños -> Daños y Contenidos. | B48: ="$"&L48&K48 -> $172.35 I.V.A. incluido | E48: =I46 -> (monto estimado en virtud de tratarse de cantidades determinadas por el Notario Público, Registro Público de la Propiedad respectivo, de acuerdo al monto de la operación). | J48: =CAT!G7 -> 172.34483 | K48: I.V.A. incluido | L48: =ROUNDUP(J48,2) -> 172.35
A50: Desempleo | B50: Gratis durante toda la vida del crédito.(1)
A52: =IF(Mujer_Banorte="Sí","Seguro de Enfermedades Graves y Momentos de Vida","") -> #REF! | B52: =IF(A52="","",""&DOLLAR(+[2]Cotización!$D$209)&" No genera I.V.A.") -> #REF!
A53: (1) Aplica si el Solicitante cubre los requisitos de elegibilidad vigentes en la póliza de vida colectiva.
A54: (2) Los valores son los referidos a cada concepto indicado en el cuerpo de la presente oferta, sin considerar I.V.A.
A55: (3) Enfermedades Graves y Momentos de Vida solo aplica cuando participa una mujer como acreditada o coacreditada al contratarse un crédito nuevo.
A57: =IF([1]Simulador!$F$11='[1]Tabla Parámetros'!$O$4,'Oferta Vinculante'!$I$57,'Oferta Vinculante'!I56) -> 0 | I57: * Sólo para Hipoteca Más por Menos: La tasa de interés es de 11.30% del mes 1 al 37, de 11.55% del mes 38 al 73, de 11.80% del mes 74 en adelante.
A58: Causas y penas por terminación anticipada:
A60: DÉCIMA SÉPTIMA:- VENCIMIENTO ANTICIPADO.- EL BANCO se reserva la facultad de dar por vencido anticipadamente el plazo fijado en la cláusula de PLAZO DEL CONTRATO, y en consecuencia, el ACREDITADO deberá hacer el pago inmediato del importe del saldo del crédito, intereses ordinarios, moratorios, gastos y demás accesorios legales, si el ACREDITADO faltare al cumplimiento de cualesquiera de las obligaciones contraídas en este contrato, o en los casos en que la Ley así lo previene, o en los siguientes supuestos:-
A64: a).- Si el ACREDITADO dejare de efectuar, en forma total, uno o más de los pagos que se obliga a realizar conforme al presente contrato, sean éstos de capital, intereses, comisiones, gastos u otros accesorios.
A66: b).- Si el ACREDITADO, vende, grava, afecta o transmite por cualquier figura jurídica los derechos de propiedad que tiene respecto del (de los) inmueble(s) dado(s) en garantía hipotecaria, excepto en caso de herencia.
A68: c).- Si el valor del (de los) bien(es) dado(s) en garantía hipotecaria se reduce un 20%-veinte por ciento o más de su valor, tomando como base el (los) avalúo(s) que para el otorgamiento del crédito hubiere mandado practicar EL BANCO de manera que no bastare(n) a cubrir el pago de capital, intereses, comisiones, gastos u otros accesorios pactados en esta escritura.
A71: d).- Si el ACREDITADO destinare el crédito a un fin distinto del expresamente señalado en la cláusula de DESTINO DEL CRÉDITO
A72: =_Inciso_Vigilancia -> 0
A73: e).- Si el(los) inmueble(s) no se inscribe(n) en el Registro Público de la Propiedad y del Comercio de conformidad con lo señalado en la cláusula de GARANTÍA(S), fuere(n) embargado(s) por terceros, o si fuere(n) gravado(s) en ulterior grado, sin autorización expresa y por escrito de EL BANCO.
A75: f).- Si el ACREDITADO introdujere modificaciones al(a los) inmueble(s) que cause(n) una disminución en el valor comercial del (de los) inmueble(s) o si por cualquier causa resultare(n) total o parcialmente destruido(s) el(los) inmueble(s).
A77: g).- Si el ACREDITADO dejare de pagar dos bimestres consecutivos del impuesto predial, o cuotas por servicios de agua o cualquier responsabilidad civil dentro de los diez días siguientes a la notificación que les fuere hecha por las autoridades respectivas.
A79: h).- Si el ACREDITADO no mantuviere vigente el(los) contrato(s) de (de los) seguro(s) en caso de que lo(s) haya contratado con una Aseguradora Externa. Así como también si el ACREDITADO no entrega la(s) póliza(s) y comprobantes de pago de las primas en los términos estipulados en la cláusula de SEGUROS.
A81: i).- Si el ACREDITADO faltare al exacto cumplimiento de las obligaciones que en general ha contraído en este instrumento.
A82: j).- En los demás casos en que conforme a la Ley se hace exigible anticipadamente el cumplimiento de las obligaciones a plazo.
A83: k).- Si el ACREDITADO deja de cumplir con cualquier otro crédito o préstamo que le hubiere otorgado EL BANCO que se dé por vencido anticipadamente o cualquier obligación crediticia a plazo que tenga el ACREDITADO con EL BANCO.
A85: l).- Si el ACREDITADO incumple con uno o más de los pagos que se encuentra obligado a cubrir de conformidad con lo establecido en el presente instrumento derivado de una reclamación presentada por el ACREDITADO con relación a cargos mal aplicados.
A87: Penas:
A88: Intereses moratorios.- Se generarán a partir del día siguiente de la fecha de vencimiento del tercer pago mensual incumplido, hasta la fecha en que se realice el pago, a la tasa de interés anual que resulte de multiplicar por 2-dos, la tasa de interés ordinaria. Si durante la vigencia del contrato vuelve a incumplir después de que se haya puesto al corriente en los pagos, se le volverá a generar el interés moratorio en los términos señalados.
A91: Comisión por cobranza.- Se generará a partir del 6-sexto día natural siguiente a la fecha de vencimiento del pago respectivo, se podrá generar hasta por tres pagos mensuales consecutivos incumplidos y se deberá cubrir al momento de su generación, y será la cantidad que resulte de aplicar el 5%-cinco por ciento sobre el saldo vencido. Si durante la vigencia del contrato vuelve a incumplir después de que se haya puesto al corriente en los pagos, se le volverá a generar la comisión por cobranza en los términos señalados. No se cobrará durante el mismo período, la comisión por cobranza conjunta con los intereses moratorios.
A95: Información relativa a riesgos inherentes al crédito garantizado a la vivienda de que se trate en relación a las posibles variaciones en tasas de interés, inflación y tipo de UDIs.
... A120: Le recordamos mantenerse al corriente en sus pagos mensuales para disfrutar de los beneficios que le ofrece su Crédito Hipotecario El Banco.
I121: =IF([1]Simulador!$F$19=180,$I$122,IF([1]Simulador!$F$19=240,$I$123,)) -> Tasa de Interés Anual Inicial del 11.3%, pago al millar inicial de $9.57 con ajuste anual del 2.12%, este incremento anual del pago al millar se aplica directamente al capital del crédito.
A122: =IF([1]Simulador!$F$11='[1]Tabla Parámetros'!$O$4,'Oferta Vinculante'!$I$121,'Oferta Vinculante'!$I$120) -> 0 | I122: Tasa de Interés Anual Inicial del 11.3%, pago al millar inicial de $10.62 con ajuste anual del 2.12%, este incremento anual del pago al millar se aplica directamente al capital del crédito.
I123: Tasa de Interés Anual Inicial del 11.3%, pago al millar inicial de $9.57 con ajuste anual del 2.12%, este incremento anual del pago al millar se aplica directamente al capital del crédito.
A124: Costo Anual Total de créditos denominados en Moneda Nacional a tasa fija para fines informativos y de comparación exclusivamente. El CAT solo es comparable con el CAT de otros créditos denominados en Moneda Nacional a tasa fija. El CAT no forma parte de los términos y condiciones del crédito, por lo que no es vinculante para la formalización del mismo.
D129: =D3 -> monterrey | E129: =E3 -> 45973
A131: El Banco
A135: Captura nombre del funcionario facultado | D135: Captura nombre del funcionario facultado
A136: Nombre y firma de funcionario facultado | D136: Nombre y firma de funcionario facultado
A138: Recibí de conformidad
A142: Capturar nombre del Solicitante
A143: Nombre y firma del Solicitante
A145: Obligaciones y Restricciones
A147: Declaro que conozco las obligaciones y restricciones que establece la Ley de Transparencia y Fomento a la Competencia en el Crédito Garantizado, para las Entidades y para los Solicitantes de crédito cuando soliciten una Oferta Vinculante, por lo cual manifiesto mi aceptación a lo siguiente:
A150: 1. Que El Banco puede analizar y tramitar mi crédito de forma normal sin necesidad de que me extienda una Oferta Vinculante.
A152: 2. Que la Oferta Vinculante tendrá una vigencia de solo 20 (veinte) días naturales a partir de que la reciba y que dentro de dicho plazo debo dar aviso por escrito de mi aceptación a la misma.
A155: 3. Que al momento de aceptar la Oferta debo presentar todos los documentos y requisitos necesarios para la contratación del crédito y presentar debidamente requisitada toda la documentación soporte de la información declarada en la solicitud.
A158: 4. Que los términos y condiciones de la Oferta, podrán modificarse si El Banco me da aviso por escrito y una vez recibido manifiesto mi aceptación con dichas modificaciones.
A161: 5. Que aún cuando fuere necesario para la aprobación del crédito El Banco no podrá solicitarme ningún documento adicional a los señalados en la solicitud de crédito, con lo cual mi crédito puede ser negado.
A164: 6. Que El Banco podrá decidir no otorgarme el crédito si no comprueba la veracidad y autenticidad de los datos proporcionados o si la información y documentación no cumple con lo establecido en la Ley.
D168: =D129 -> monterrey | E168: =E129 -> 45973
A170: Firma de conformidad
A174: Capturar nombre del Solicitante
A175: Nombre y firma del Solicitante

Sheet Fecha Pago
A1: Fecha Corte | B1: 3 | F1: Salida Combo | G1: Plazo | H1: =Carátula!$H$29 -> 240
A2: Fecha Cotización | B2: =Carátula!$F$7 -> 45973 | F2: Fórmula | G2: Días PMT | H2: 30.4 | N2: =IF(OR(B3=30,B3=31),30,0) -> 0
A3: Día Fecha Cotización | B3: =DAY($B$2) -> 12 | C3: =B3 -> 12 | D3: =$B3-$C3 -> 0 | K3: =B2 -> 45973 | L3: Duración Intereses
A4: Mes Fecha Cotización | B4: =MONTH($B$2) -> 11 | C4: =B4 -> 11 | D4: =$B4-$C4 -> 0 | J4: 1 | K4: =IF(($J$4:$J$363)<=$H$1,(EOMONTH(K3,0)+$B$6+N2)) -> 45994 | L4: =$K$1:$K$363 - $B$2 + 1 -> 22
A5: Año Fecha Cotización | B5: =YEAR($B$2) -> 2025 | C5: =B5 -> 2025 | D5: =$B5-$C5 -> 0 | J5: 2 | K5: =IF(($J$4:$J$363)<=$H$1,(EOMONTH(K4,0)+$B$6)) -> 46025 | L5: =IF($J$4:$J$363 <= $H$1,$H$2,"") -> 30.4
A6: Día Primer Pago | B6: 3 | D6: =IF(SUM($D$3:$D$5)<>0,"SI","NO") -> NO | E6: Fecha Diferente / Se utiliza para validar fecha de captura | J6: 3 | K6: =IF(($J$4:$J$363)<=$H$1,(EOMONTH(K5,0)+$B$6)) -> 46056 | L6: =IF($J$4:$J$363 <= $H$1,$H$2,"") -> 30.4
A7: Mes Primer Pago | B7: =MONTH(B2)+1 -> 12 | J7: 4 | K7: =IF(($J$4:$J$363)<=$H$1,(EOMONTH(K6,0)+$B$6)) -> 46084 | L7: =IF($J$4:$J$363 <= $H$1,$H$2,"") -> 30.4
A8: Fecha Primer Pago | B8: =DATE(B5,B7,B6) -> 45994 | J8: 5 | K8: =IF(($J$4:$J$363)<=$H$1,(EOMONTH(K7,0)+$B$6)) -> 46115 | L8: =IF($J$4:$J$363 <= $H$1,$H$2,"") -> 30.4
B9: Día | C9: Mes | D9: Año | J9: 6 | K9: =IF(($J$4:$J$363)<=$H$1,(EOMONTH(K8,0)+$B$6)) -> 46145 | L9: =IF($J$4:$J$363 <= $H$1,$H$2,"") -> 30.4
B10: =B3 -> 12 | C10: =B4 -> 11 | D10: =VLOOKUP($D$11,$A$12:$D$42,4,FALSE) -> 2026 | J10: 7 | K10: =IF(($J$4:$J$363)<=$H$1,(EOMONTH(K9,0)+$B$6)) -> 46176 | L10: =IF($J$4:$J$363 <= $H$1,$H$2,"") -> 30.4
D11: 1 | F11: Día máximo | G11: =+VLOOKUP(C4,E12:F23,2) -> 30 | J11: 8 | K11: =IF(($J$4:$J$363)<=$H$1,(EOMONTH(K10,0)+$B$6)) -> 46206 | L11: =IF($J$4:$J$363 <= $H$1,$H$2,"") -> 30.4
A12: 1 | B12: 1 | C12: Enero | D12: =YEAR(TODAY()) -> 2026 | E12: 1 | F12: 31 | J12: 9 | K12: =IF(($J$4:$J$363)<=$H$1,(EOMONTH(K11,0)+$B$6)) -> 46237 | L12: =IF($J$4:$J$363 <= $H$1,$H$2,"") -> 30.4
A13: 2 | B13: 2 | C13: Febrero | D13: =+D12+1 -> 2027 | E13: 2 | F13: 28 | J13: 10 | K13: =IF(($J$4:$J$363)<=$H$1,(EOMONTH(K12,0)+$B$6)) -> 46268 | L13: =IF($J$4:$J$363 <= $H$1,$H$2,"") -> 30.4
A14: 3 | B14: 3 | C14: Marzo | D14: =+D13+1 -> 2028 | E14: 3 | F14: 31 | J14: 11 | K14: =IF(($J$4:$J$363)<=$H$1,(EOMONTH(K13,0)+$B$6)) -> 46298 | L14: =IF($J$4:$J$363 <= $H$1,$H$2,"") -> 30.4
A15: 4 | B15: 4 | C15: Abril | D15: =+D14+1 -> 2029 | E15: 4 | F15: 30 | J15: 12 | K15: =IF(($J$4:$J$363)<=$H$1,(EOMONTH(K14,0)+$B$6)) -> 46329 | L15: =IF($J$4:$J$363 <= $H$1,$H$2,"") -> 30.4
A16: 5 | B16: 5 | C16: Mayo | D16: =+D15+1 -> 2030 | E16: 5 | F16: 31 | J16: 13 | K16: =IF(($J$4:$J$363)<=$H$1,(EOMONTH(K15,0)+$B$6)) -> 46359 | L16: =IF($J$4:$J$363 <= $H$1,$H$2,"") -> 30.4
A17: 6 | B17: 6 | C17: Junio | E17: 6 | F17: 30 | J17: 14 | K17: =IF(($J$4:$J$363)<=$H$1,(EOMONTH(K16,0)+$B$6)) -> 46390 | L17: =IF($J$4:$J$363 <= $H$1,$H$2,"") -> 30.4
A18: 7 | B18: 7 | C18: Julio | E18: 7 | F18: 31 | J18: 15 | K18: =IF(($J$4:$J$363)<=$H$1,(EOMONTH(K17,0)+$B$6)) -> 46421 | L18: =IF($J$4:$J$363 <= $H$1,$H$2,"") -> 30.4
A19: 8 | B19: 8 | C19: Agosto | E19: 8 | F19: 31 | J19: 16 | K19: =IF(($J$4:$J$363)<=$H$1,(EOMONTH(K18,0)+$B$6)) -> 46449 | L19: =IF($J$4:$J$363 <= $H$1,$H$2,"") -> 30.4
A20: 9 | B20: 9 | C20: Septiembre | E20: 9 | F20: 30 | J20: 17 | K20: =IF(($J$4:$J$363)<=$H$1,(EOMONTH(K19,0)+$B$6)) -> 46480 | L20: =IF($J$4:$J$363 <= $H$1,$H$2,"") -> 30.4
A21: 10 | B21: 10 | C21: Octubre | E21: 10 | F21: 31 | J21: 18 | K21: =IF(($J$4:$J$363)<=$H$1,(EOMONTH(K20,0)+$B$6)) -> 46510 | L21: =IF($J$4:$J$363 <= $H$1,$H$2,"") -> 30.4
A22: 11 | B22: 11 | C22: Noviembre | E22: 11 | F22: 30 | J22: 19 | K22: =IF(($J$4:$J$363)<=$H$1,(EOMONTH(K21,0)+$B$6)) -> 46541 | L22: =IF($J$4:$J$363 <= $H$1,$H$2,"") -> 30.4
A23: 12 | B23: 12 | C23: Diciembre | E23: 12 | F23: 31 | J23: 20 | K23: =IF(($J$4:$J$363)<=$H$1,(EOMONTH(K22,0)+$B$6)) -> 46571 | L23: =IF($J$4:$J$363 <= $H$1,$H$2,"") -> 30.4
A24: 13 | B24: 13 | J24: 21 | K24: =IF(($J$4:$J$363)<=$H$1,(EOMONTH(K23,0)+$B$6)) -> 46602 | L24: =IF($J$4:$J$363 <= $H$1,$H$2,"") -> 30.4
A25: 14 | B25: 14 | J25: 22 | K25: =IF(($J$4:$J$363)<=$H$1,(EOMONTH(K24,0)+$B$6)) -> 46633 | L25: =IF($J$4:$J$363 <= $H$1,$H$2,"") -> 30.4
A26: 15 | B26: 15 | J26: 23 | K26: =IF(($J$4:$J$363)<=$H$1,(EOMONTH(K25,0)+$B$6)) -> 46663 | L26: =IF($J$4:$J$363 <= $H$1,$H$2,"") -> 30.4
A27: 16 | B27: 16 | J27: 24 | K27: =IF(($J$4:$J$363)<=$H$1,(EOMONTH(K26,0)+$B$6)) -> 46694 | L27: =IF($J$4:$J$363 <= $H$1,$H$2,"") -> 30.4
A28: 17 | B28: 17 | J28: 25 | K28: =IF(($J$4:$J$363)<=$H$1,(EOMONTH(K27,0)+$B$6)) -> 46724 | L28: =IF($J$4:$J$363 <= $H$1,$H$2,"") -> 30.4
A29: 18 | B29: 18 | J29: 26 | K29: =IF(($J$4:$J$363)<=$H$1,(EOMONTH(K28,0)+$B$6)) -> 46755 | L29: =IF($J$4:$J$363 <= $H$1,$H$2,"") -> 30.4
A30: 19 | B30: 19 | J30: 27 | K30: =IF(($J$4:$J$363)<=$H$1,(EOMONTH(K29,0)+$B$6)) -> 46786 | L30: =IF($J$4:$J$363 <= $H$1,$H$2,"") -> 30.4
A31: 20 | B31: 20 | J31: 28 | K31: =IF(($J$4:$J$363)<=$H$1,(EOMONTH(K30,0)+$B$6)) -> 46815 | L31: =IF($J$4:$J$363 <= $H$1,$H$2,"") -> 30.4
A32: 21 | B32: 21 | J32: 29 | K32: =IF(($J$4:$J$363)<=$H$1,(EOMONTH(K31,0)+$B$6)) -> 46846 | L32: =IF($J$4:$J$363 <= $H$1,$H$2,"") -> 30.4
A33: 22 | B33: 22 | J33: 30 | K33: =IF(($J$4:$J$363)<=$H$1,(EOMONTH(K32,0)+$B$6)) -> 46876 | L33: =IF($J$4:$J$363 <= $H$1,$H$2,"") -> 30.4
A34: 23 | B34: 23 | J34: 31 | K34: =IF(($J$4:$J$363)<=$H$1,(EOMONTH(K33,0)+$B$6)) -> 46907 | L34: =IF($J$4:$J$363 <= $H$1,$H$2,"") -> 30.4
A35: 24 | B35: 24 | J35: 32 | K35: =IF(($J$4:$J$363)<=$H$1,(EOMONTH(K34,0)+$B$6)) -> 46937 | L35: =IF($J$4:$J$363 <= $H$1,$H$2,"") -> 30.4
... A41: 30 | B41: 30 | J41: 38 | K41: =IF(($J$4:$J$363)<=$H$1,(EOMONTH(K40,0)+$B$6)) -> 47121 | L41: =IF($J$4:$J$363 <= $H$1,$H$2,"") -> 30.4
A42: 31 | J42: 39 | K42: =IF(($J$4:$J$363)<=$H$1,(EOMONTH(K41,0)+$B$6)) -> 47152 | L42: =IF($J$4:$J$363 <= $H$1,$H$2,"") -> 30.4
J43: 40 | K43: =IF(($J$4:$J$363)<=$H$1,(EOMONTH(K42,0)+$B$6)) -> 47180 | L43: =IF($J$4:$J$363 <= $H$1,$H$2,"") -> 30.4
J44: 41 | K44: =IF(($J$4:$J$363)<=$H$1,(EOMONTH(K43,0)+$B$6)) -> 47211 | L44: =IF($J$4:$J$363 <= $H$1,$H$2,"") -> 30.4
J45: 42 | K45: =IF(($J$4:$J$363)<=$H$1,(EOMONTH(K44,0)+$B$6)) -> 47241 | L45: =IF($J$4:$J$363 <= $H$1,$H$2,"") -> 30.4
J46: 43 | K46: =IF(($J$4:$J$363)<=$H$1,(EOMONTH(K45,0)+$B$6)) -> 47272 | L46: =IF($J$4:$J$363 <= $H$1,$H$2,"") -> 30.4
J47: 44 | K47: =IF(($J$4:$J$363)<=$H$1,(EOMONTH(K46,0)+$B$6)) -> 47302 | L47: =IF($J$4:$J$363 <= $H$1,$H$2,"") -> 30.4
J48: 45 | K48: =IF(($J$4:$J$363)<=$H$1,(EOMONTH(K47,0)+$B$6)) -> 47333 | L48: =IF($J$4:$J$363 <= $H$1,$H$2,"") -> 30.4
J49: 46 | K49: =IF(($J$4:$J$363)<=$H$1,(EOMONTH(K48,0)+$B$6)) -> 47364 | L49: =IF($J$4:$J$363 <= $H$1,$H$2,"") -> 30.4
J50: 47 | K50: =IF(($J$4:$J$363)<=$H$1,(EOMONTH(K49,0)+$B$6)) -> 47394 | L50: =IF($J$4:$J$363 <= $H$1,$H$2,"") -> 30.4
J51: 48 | K51: =IF(($J$4:$J$363)<=$H$1,(EOMONTH(K50,0)+$B$6)) -> 47425 | L51: =IF($J$4:$J$363 <= $H$1,$H$2,"") -> 30.4
J52: 49 | K52: =IF(($J$4:$J$363)<=$H$1,(EOMONTH(K51,0)+$B$6)) -> 47455 | L52: =IF($J$4:$J$363 <= $H$1,$H$2,"") -> 30.4
J53: 50 | K53: =IF(($J$4:$J$363)<=$H$1,(EOMONTH(K52,0)+$B$6)) -> 47486 | L53: =IF($J$4:$J$363 <= $H$1,$H$2,"") -> 30.4
J54: 51 | K54: =IF(($J$4:$J$363)<=$H$1,(EOMONTH(K53,0)+$B$6)) -> 47517 | L54: =IF($J$4:$J$363 <= $H$1,$H$2,"") -> 30.4
... J363: 360 | K363: =IF(($J$4:$J$363)<=$H$1,(EOMONTH(K362,0)+$B$6)) -> FALSE | L363: =IF($J$4:$J$363 <= $H$1,$H$2,"")

Sheet Notariales Estados
A1: ESTADO | B1: SOLO COMPRA VENTA | C1: SOLO CREDITO | D1: SUMA (Compraventa con crédito) | E1: =VLOOKUP(Carátula!$N$13,'Notariales Estados'!A2:D33,3,0) -> 0.022 | F1: Mejora + Remodelación | G1: =VLOOKUP(Carátula!$N$13,'Notariales Estados'!F2:G33,2,0) -> 12931.034
A2: Aguascalientes | B2: 0.023 | C2: 0.016 | D2: 0.039 | F2: Aguascalientes | G2: 7000
A3: Baja California Norte | B3: 0.05 | C3: 0.01 | D3: 0.06 | F3: Baja California Norte | G3: 5000
A4: Baja California Sur | B4: 0.036 | C4: 0.008 | D4: 0.044 | F4: Baja California Sur | G4: 5000
A5: Campeche | B5: 0.0187 | C5: 0.012 | D5: 0.0307 | F5: Campeche | G5: 5000
A6: Chiapas | B6: 0.0365 | C6: 0.0068 | D6: 0.0433 | F6: Chiapas | G6: 5000
A7: Chihuahua | B7: 0.054 | C7: 0.016 | D7: 0.07 | F7: Chihuahua | G7: 5000
A8: Ciudad de México | B8: 0.06 | C8: 0.022 | D8: 0.082 | F8: Coahuila | G8: 5000
A9: Coahuila | B9: 0.0519 | C9: 0.021 | D9: 0.0729 | F9: Colima | G9: 4000
A10: Colima | B10: 0.0286 | C10: 0.0121 | D10: 0.0407 | F10: Ciudad de México | G10: 12931.034
A11: Durango | B11: 0.05 | C11: 0.014 | D11: 0.064 | F11: Durango | G11: 5000
A12: Estado de México | B12: 0.065 | C12: 0.022 | D12: 0.087 | F12: Estado de México | G12: 12931.034
A13: Guanajuato | B13: 0.02 | C13: 0.011 | D13: =IF(G5="SI",I13,3.1%) -> 0.031 | F13: Guanajuato | G13: 5000
A14: Guerrero | B14: 0.05 | C14: 0.015 | D14: 0.065 | F14: Guerrero | G14: 5000
A15: Hidalgo | B15: 0.05 | C15: 0.02 | D15: 0.07 | F15: Hidalgo | G15: 5000
A16: Jalisco | B16: 0.045 | C16: 0.018 | D16: 0.063 | F16: Jalisco | G16: 5000
A17: Michoacán | B17: 0.026 | C17: 0.014 | D17: 0.04 | F17: Michoacán | G17: 5000
A18: Morelos | B18: 0.045 | C18: 0.012 | D18: 0.057 | F18: Morelos | G18: 5000
A19: Nayarit | B19: 0.037 | C19: 0.011 | D19: 0.048 | F19: Nayarit | G19: 5000
A20: Nuevo León | B20: 0.0445 | C20: 0.0155 | D20: 0.06 | F20: Nuevo León | G20: 5000
A21: Oaxaca | B21: 0.0347 | C21: 0.0076 | D21: 0.0422 | F21: Oaxaca | G21: 7000
A22: Puebla | B22: 0.05 | C22: 0.04 | D22: 0.09 | F22: Puebla | G22: 5000
A23: Querétaro | B23: 0.075 | C23: 0.012 | D23: 0.087 | F23: Querétaro | G23: 5000
A24: Quintana Roo | B24: 0.05 | C24: 0.02 | D24: 0.07 | F24: Quintana Roo | G24: 5000
A25: San Luis Potosí | B25: 0.051 | C25: 0.014 | D25: 0.065 | F25: San Luis Potosí | G25: 6465.5172
... A28: Tabasco | B28: 0.0526 | C28: 0.0074 | D28: 0.06 | F28: Tabasco | G28: 5000
A29: Tamaulipas | B29: 0.04 | C29: 0.02 | D29: =B29+C29 -> 0.06 | F29: Tamaulipas | G29: 5000
A30: Tlaxcala | B30: 0.0305 | C30: 0.0101 | D30: 0.0406 | F30: Tlaxcala | G30: 5000
A31: Veracruz | B31: 0.0245 | C31: 0.021 | D31: 0.0455 | F31: Veracruz | G31: 7000
A32: Yucatán | B32: 0.0396 | C32: 0.0081 | D32: 0.0477 | F32: Yucatán | G32: 5000
A33: Zacatecas | B33: 0.035 | C33: 0.015 | D33: 0.05 | F33: Zacatecas | G33: 5000

Sheet Catálogos
B1: Plazo | D1: Seguro | F1: CXA | H1: Estado | J1: Tasa | K1: =VLOOKUP(Carátula!$E$39,Catálogos!J2:K6,2,0) -> 1 | M1: Prepago | Q1: Factores Seguro Vida | R1: =VLOOKUP(Carátula!H31,Catálogos!P2:Q3,2,0) -> 0.0006
B2: 60 | D2: Básico | F2: SI | H2: Aguascalientes | J2: 0.0915 | K2: 1 | M2: Reduce Plazo y Pago | N2: 1 | P2: Básico | Q2: 0.0006
B3: 72 | D3: Amplio | F3: NO | H3: Baja California Norte | J3: 0.0985 | K3: 1 | M3: Reduce Plazo | N3: 2 | P3: Amplio | Q3: 0.0008583
B4: 84 | H4: Baja California Sur | J4: 0.1015 | K4: 2 | M4: Reduce Pago | N4: 3 | Q4: Factores Seguro Daños | R4: =IF(OR(Carátula!$I$15="SI",Catálogos!$R$12=2),0,0.00028) -> 0.00028
B5: 96 | H5: Campeche | J5: 0.1055 | K5: 2 | Q5: 0.00028
B6: 108 | H6: Chiapas | J6: 0.1115 | K6: 2 | M6: Prepago | N6: =VLOOKUP(Carátula!N39,Catálogos!M2:N4,2,0) -> 1 | P6: Sin IVA | Q6: =Q5/1.16 -> 0.00024137931
B7: 120 | H7: Chihuahua
B8: 132 | H8: Ciudad de México
B9: 144 | H9: Coahuila | M9: Comisión Prepago | N9: 0
B10: 156 | H10: Colima | J10: Destinos | K10: =VLOOKUP(Carátula!I35,Catálogos!$J$10:$K$12,2,0) -> 1 | N10: =IF(K1=1,Catálogos!N9,0) -> 0
B11: 168 | H11: Durango | J11: Mejora de Hipoteca | K11: 1
B12: 180 | H12: Estado de México | J12: Liquidez | K12: 2 | R12: =VLOOKUP(Carátula!I35,Catálogos!Q13:R14,2,0) -> 1
B13: 192 | H13: Guanajuato | J13: =IF($K$10=1,L13,IF(K10=2,L13,"")) -> Recuerda que el Aforo Máximo es 85% | K13: 0.85 | L13: Recuerda que el Aforo Máximo es 85% | Q13: Mejora de Hipoteca | R13: 1
B14: 204 | H14: Guerrero | J14: =IF(K15>K18,J13,"") | Q14: Liquidez | R14: 2
B15: 216 | H15: Hidalgo | K15: =IF(K10=1,O16,O17) -> 0.58823529
B16: 228 | H16: Jalisco | J16: Mejora Más Liquidez | K16: 0.85 | L16: =Carátula!$F$15 -> 1020000 | M16: =K16*Carátula!F15 -> 867000 | N16: =Carátula!F19 -> 600000 | O16: =N16/L16 -> 0.58823529
B17: 240 | H17: Michoacán | J17: Liquidez | K17: 0.45 | L17: =Carátula!$F$15 -> 1020000 | M17: =K17*Carátula!F15 -> 459000 | N17: =Carátula!F21 -> 250000 | O17: =N17/L17 -> 0.24509804
H18: Morelos | K18: =IF(K10=1,K16,K17) -> 0.85
H19: Nayarit
H20: Nuevo León
H21: Oaxaca | K21: Calculo de Liquidez
H22: Puebla | K22: LTV Máx | L22: Valor vivienda | M22: Valor LTV Máx M + L | N22: Valor LTV Máx Liquidez
H23: Querétaro | K23: 0.85 | L23: =Carátula!$F$15 -> 1020000 | M23: =L23*K23 -> 867000 | N23: =L23*K25 -> 459000
H24: Quintana Roo | K24: LTV Máx L | L24: Monto Mejora | M24: =L25+L27 -> 850000 | N24: =M23-L25 -> 267000
H25: San Luis Potosí | K25: 0.45 | L25: =Carátula!$F$19 -> 600000
H26: Sinaloa | L26: Monto Líquidez
H27: Sonora | L27: =Carátula!$F$21 -> 250000
H28: Tabasco
H29: Tamaulipas
H30: Tlaxcala
H31: Veracruz
H32: Yucatán
H33: Zacatecas

Sheet Avalúos
A1: Parametros avalúo
A3: Comisión Avalúo Escalonada
H4: Resultados
A5: Parámetros | H5: Tarifa por Valor | I5: =VLOOKUP(B6,A12:C20,3,TRUE) -> 5000
A6: Valor Avalúo | B6: =Carátula!$F$15 -> 1020000 | I6: =IF(B6>10000000,I5/2,0) -> 0
A11: Mínimo | B11: Máximo | C11: Costo sin IVA
A12: 0 | B12: 1000000 | C12: 3000
A13: 1000001 | B13: 3000000 | C13: 5000
A14: 3000001 | B14: 5000000 | C14: 8000
A15: 5000001 | B15: 7000000 | C15: 15000
A16: 7000001 | B16: 10000000 | C16: 17000
A17: 10000001 | B17: 20000000 | C17: 25000
A18: 20000001 | B18: 30000000 | C18: 30000
A19: 30000001 | B19: 100000000 | C19: =B6*0.001 -> 1020
A20: 100000001 | B20: 999999999 | C20: =B6*0.001 -> 1020

Sheet Prepagos
C1: 1 | D1: 2 | E1: 3 | G1: Plazo | H1: =Carátula!$H$29 -> 240 | J1: Reduce Plazo y Pago | K1: 1
B2: Capital | C2: =J1 -> Reduce Plazo y Pago | D2: =J2 -> Reduce Plazo | E2: =J3 -> Reduce Pago | G2: Tasa | H2: =Carátula!$E$39 -> 0.0915 | J2: Reduce Plazo | K2: 2
A3: 1 | B3: =H3 -> 600000 | C3: =IF(A3="","",PPMT($H$2/360*30.4,A3,$H$1,-$H$3)+Carátula!M44-Carátula!N44) -> 867.75904 | D3: =IF(A3="","",((PMT($H$2/360*30.4,$H$1,-$H$3))-(($H$2/360*30.4)*(B3)))+Carátula!M44-Carátula!N44) -> 867.75904 | E3: =IF(A3="","",PPMT($H$2/360*30.4,1,$H$1-A3+1,-B3)+Carátula!M44-Carátula!N44) -> 867.75904 | G3: Crédito | H3: =Carátula!$F$44 -> 600000 | J3: Reduce Pago | K3: 3
A4: =IF(A3=$H$1,"",IF(A3="","",A3+1)) -> 2 | B4: =Carátula!F45 -> 599132.24 | C4: =IF(A4="","",PPMT($H$2/360*30.4,A4,$H$1,-$H$3)+Carátula!M45-Carátula!N45) -> 874.46393 | D4: =IF(A4="","",(PMT($H$2/360*30.4,$H$1,-$H$3)-(($H$2/360*30.4)*(B4))+Carátula!M45-Carátula!N45)) -> 874.46393 | E4: =IF(A4="","",PPMT($H$2/360*30.4,1,$H$1-A4+1,-B4)+Carátula!M45-Carátula!N45) -> 874.46393
A5: =IF(A4=$H$1,"",IF(A4="","",A4+1)) -> 3 | B5: =Carátula!F46 -> 598257.78 | C5: =IF(A5="","",PPMT($H$2/360*30.4,A5,$H$1,-$H$3)+Carátula!M46-Carátula!N46) -> 881.22062 | D5: =IF(A5="","",(PMT($H$2/360*30.4,$H$1,-$H$3)-(($H$2/360*30.4)*(B5))+Carátula!M46-Carátula!N46)) -> 881.22062 | E5: =IF(A5="","",PPMT($H$2/360*30.4,1,$H$1-A5+1,-B5)+Carátula!M46-Carátula!N46) -> 881.22062
A6: =IF(A5=$H$1,"",IF(A5="","",A5+1)) -> 4 | B6: =Carátula!F47 -> 597376.56 | C6: =IF(A6="","",PPMT($H$2/360*30.4,A6,$H$1,-$H$3)+Carátula!M47-Carátula!N47) -> 888.02952 | D6: =IF(A6="","",(PMT($H$2/360*30.4,$H$1,-$H$3)-(($H$2/360*30.4)*(B6))+Carátula!M47-Carátula!N47)) -> 888.02952 | E6: =IF(A6="","",PPMT($H$2/360*30.4,1,$H$1-A6+1,-B6)+Carátula!M47-Carátula!N47) -> 888.02952
A7: =IF(A6=$H$1,"",IF(A6="","",A6+1)) -> 5 | B7: =Carátula!F48 -> 596488.53 | C7: =IF(A7="","",PPMT($H$2/360*30.4,A7,$H$1,-$H$3)+Carátula!M48-Carátula!N48) -> 894.89102 | D7: =IF(A7="","",(PMT($H$2/360*30.4,$H$1,-$H$3)-(($H$2/360*30.4)*(B7))+Carátula!M48-Carátula!N48)) -> 894.89102 | E7: =IF(A7="","",PPMT($H$2/360*30.4,1,$H$1-A7+1,-B7)+Carátula!M48-Carátula!N48) -> 894.89102
A8: =IF(A7=$H$1,"",IF(A7="","",A7+1)) -> 6 | B8: =Carátula!F49 -> 595593.64 | C8: =IF(A8="","",PPMT($H$2/360*30.4,A8,$H$1,-$H$3)+Carátula!M49-Carátula!N49) -> 901.80555 | D8: =IF(A8="","",(PMT($H$2/360*30.4,$H$1,-$H$3)-(($H$2/360*30.4)*(B8))+Carátula!M49-Carátula!N49)) -> 901.80555 | E8: =IF(A8="","",PPMT($H$2/360*30.4,1,$H$1-A8+1,-B8)+Carátula!M49-Carátula!N49) -> 901.80555
A9: =IF(A8=$H$1,"",IF(A8="","",A8+1)) -> 7 | B9: =Carátula!F50 -> 594691.83 | C9: =IF(A9="","",PPMT($H$2/360*30.4,A9,$H$1,-$H$3)+Carátula!M50-Carátula!N50) -> 908.7735 | D9: =IF(A9="","",(PMT($H$2/360*30.4,$H$1,-$H$3)-(($H$2/360*30.4)*(B9))+Carátula!M50-Carátula!N50)) -> 908.7735 | E9: =IF(A9="","",PPMT($H$2/360*30.4,1,$H$1-A9+1,-B9)+Carátula!M50-Carátula!N50) -> 908.7735
A10: =IF(A9=$H$1,"",IF(A9="","",A9+1)) -> 8 | B10: =Carátula!F51 -> 593783.06 | C10: =IF(A10="","",PPMT($H$2/360*30.4,A10,$H$1,-$H$3)+Carátula!M51-Carátula!N51) -> 915.79529 | D10: =IF(A10="","",(PMT($H$2/360*30.4,$H$1,-$H$3)-(($H$2/360*30.4)*(B10))+Carátula!M51-Carátula!N51)) -> 915.79529 | E10: =IF(A10="","",PPMT($H$2/360*30.4,1,$H$1-A10+1,-B10)+Carátula!M51-Carátula!N51) -> 915.79529
A11: =IF(A10=$H$1,"",IF(A10="","",A10+1)) -> 9 | B11: =Carátula!F52 -> 592867.26 | C11: =IF(A11="","",PPMT($H$2/360*30.4,A11,$H$1,-$H$3)+Carátula!M52-Carátula!N52) -> 922.87133 | D11: =IF(A11="","",(PMT($H$2/360*30.4,$H$1,-$H$3)-(($H$2/360*30.4)*(B11))+Carátula!M52-Carátula!N52)) -> 922.87133 | E11: =IF(A11="","",PPMT($H$2/360*30.4,1,$H$1-A11+1,-B11)+Carátula!M52-Carátula!N52) -> 922.87133
A12: =IF(A11=$H$1,"",IF(A11="","",A11+1)) -> 10 | B12: =Carátula!F53 -> 591944.39 | C12: =IF(A12="","",PPMT($H$2/360*30.4,A12,$H$1,-$H$3)+Carátula!M53-Carátula!N53) -> 930.00205 | D12: =IF(A12="","",(PMT($H$2/360*30.4,$H$1,-$H$3)-(($H$2/360*30.4)*(B12))+Carátula!M53-Carátula!N53)) -> 930.00205 | E12: =IF(A12="","",PPMT($H$2/360*30.4,1,$H$1-A12+1,-B12)+Carátula!M53-Carátula!N53) -> 930.00205
A13: =IF(A12=$H$1,"",IF(A12="","",A12+1)) -> 11 | B13: =Carátula!F54 -> 591014.39 | C13: =IF(A13="","",PPMT($H$2/360*30.4,A13,$H$1,-$H$3)+Carátula!M54-Carátula!N54) -> 937.18787 | D13: =IF(A13="","",(PMT($H$2/360*30.4,$H$1,-$H$3)-(($H$2/360*30.4)*(B13))+Carátula!M54-Carátula!N54)) -> 937.18787 | E13: =IF(A13="","",PPMT($H$2/360*30.4,1,$H$1-A13+1,-B13)+Carátula!M54-Carátula!N54) -> 937.18787
A14: =IF(A13=$H$1,"",IF(A13="","",A13+1)) -> 12 | B14: =Carátula!F55 -> 590077.2 | C14: =IF(A14="","",PPMT($H$2/360*30.4,A14,$H$1,-$H$3)+Carátula!M55-Carátula!N55) -> 944.42921 | D14: =IF(A14="","",(PMT($H$2/360*30.4,$H$1,-$H$3)-(($H$2/360*30.4)*(B14))+Carátula!M55-Carátula!N55)) -> 944.42921 | E14: =IF(A14="","",PPMT($H$2/360*30.4,1,$H$1-A14+1,-B14)+Carátula!M55-Carátula!N55) -> 944.42921
A15: =IF(A14=$H$1,"",IF(A14="","",A14+1)) -> 13 | B15: =Carátula!F56 -> 589132.77 | C15: =IF(A15="","",PPMT($H$2/360*30.4,A15,$H$1,-$H$3)+Carátula!M56-Carátula!N56) -> 951.7265 | D15: =IF(A15="","",(PMT($H$2/360*30.4,$H$1,-$H$3)-(($H$2/360*30.4)*(B15))+Carátula!M56-Carátula!N56)) -> 951.7265 | E15: =IF(A15="","",PPMT($H$2/360*30.4,1,$H$1-A15+1,-B15)+Carátula!M56-Carátula!N56) -> 951.7265
... A242: =IF(A241=$H$1,"",IF(A241="","",A241+1)) -> 240 | B242: =Carátula!F283 -> 5461.5594 | C242: =IF(A242="","",PPMT($H$2/360*30.4,A242,$H$1,-$H$3)+Carátula!M283-Carátula!N283) -> 5461.5594 | D242: =IF(A242="","",(PMT($H$2/360*30.4,$H$1,-$H$3)-(($H$2/360*30.4)*(B242))+Carátula!M283-Carátula!N283)) -> 5461.5594 | E242: =IF(A242="","",PPMT($H$2/360*30.4,1,$H$1-A242+1,-B242)+Carátula!M283-Carátula!N283) -> 5461.5594

Sheet CAT
A1: Plazo | B1: =Carátula!$H$29 -> 240 | N1: Flujo Cero
A2: Tasa | B2: =Carátula!$E$39 -> 0.0915 | G2: =Catálogos!R12 -> 1 | N2: CXA | O2: =Carátula!$L$26 -> 0
A3: Crédito | B3: =Carátula!$F$44 -> 600000 | N3: Avalúo | O3: =IF(G2=1,Avalúos!I6,0) -> 0
A4: Destructible | B4: =IF(Catálogos!$K$10=2,0,Carátula!$F$17) -> 714000 | N4: Investigación | O4: =IF(G2=1,Carátula!$L$30/1.16,0) -> 646.55172
O5: =SUM(O2:O4) -> 646.55172
B6: Saldo | C6: Capital | D6: Intereses | E6: Pago | F6: Seguro Vida | G6: Seguro Daños | H6: Comisión | I6: Mensualidad | J6: =-B3+O5 -> -599353.45 | K6: =IRR(J6:J246,0) -> 0.0093228221 | L6: TIR
A7: 1 | B7: =B3 -> 600000 | C7: =IF(A7="","",E7-D7) -> 867.75904 | D7: =IF(A7="","",($B$2/360*30.4)*B7) -> 4636 | E7: =IF(A7="","",PMT($B$2/360*30.4,$B$1,-$B$3)) -> 5503.759 | F7: =IF(A7="","",B7*Catálogos!$R$1) -> 360 | G7: =IF(A7="","",IF(B7=0,0,$B$4*Catálogos!$Q$6)) -> 172.34483 | H7: =IF(A7="","",IF($G$2=1,299,0)) -> 299 | I7: =IF(A7="","",SUM(E7:H7)) -> 6335.1039 | J7: =I7 -> 6335.1039 | K7: =K6*12 -> 0.11187386 | L7: TIR ANUAL
A8: =IF(A7=$B$1,"",IF(A7="","",A7+1)) -> 2 | B8: =IF(A8="","",B7-C7) -> 599132.24 | C8: =IF(A8="","",E8-D8) -> 874.46393 | D8: =IF(A8="","",($B$2/360*30.4)*B8) -> 4629.2951 | E8: =IF(A8="","",PMT($B$2/360*30.4,$B$1,-$B$3)) -> 5503.759 | F8: =IF(A8="","",B8*Catálogos!$R$1) -> 359.47934 | G8: =IF(A8="","",IF(B8=0,0,$B$4*Catálogos!$Q$6)) -> 172.34483 | H8: =IF(A8="","",IF($G$2=1,299,0)) -> 299 | I8: =IF(A8="","",SUM(E8:H8)) -> 6334.5832 | J8: =I8 -> 6334.5832 | K8: =EFFECT(K7,12) -> 0.11779232 | L8: INTERES EFECTIVO (CAT)
A9: =IF(A8=$B$1,"",IF(A8="","",A8+1)) -> 3 | B9: =IF(A9="","",B8-C8) -> 598257.78 | C9: =IF(A9="","",E9-D9) -> 881.22062 | D9: =IF(A9="","",($B$2/360*30.4)*B9) -> 4622.5384 | E9: =IF(A9="","",PMT($B$2/360*30.4,$B$1,-$B$3)) -> 5503.759 | F9: =IF(A9="","",B9*Catálogos!$R$1) -> 358.95467 | G9: =IF(A9="","",IF(B9=0,0,$B$4*Catálogos!$Q$6)) -> 172.34483 | H9: =IF(A9="","",IF($G$2=1,299,0)) -> 299 | I9: =IF(A9="","",SUM(E9:H9)) -> 6334.0585 | J9: =I9 -> 6334.0585
A10: =IF(A9=$B$1,"",IF(A9="","",A9+1)) -> 4 | B10: =IF(A10="","",B9-C9) -> 597376.56 | C10: =IF(A10="","",E10-D10) -> 888.02952 | D10: =IF(A10="","",($B$2/360*30.4)*B10) -> 4615.7295 | E10: =IF(A10="","",PMT($B$2/360*30.4,$B$1,-$B$3)) -> 5503.759 | F10: =IF(A10="","",B10*Catálogos!$R$1) -> 358.42593 | G10: =IF(A10="","",IF(B10=0,0,$B$4*Catálogos!$Q$6)) -> 172.34483 | H10: =IF(A10="","",IF($G$2=1,299,0)) -> 299 | I10: =IF(A10="","",SUM(E10:H10)) -> 6333.5298 | J10: =I10 -> 6333.5298
A11: =IF(A10=$B$1,"",IF(A10="","",A10+1)) -> 5 | B11: =IF(A11="","",B10-C10) -> 596488.53 | C11: =IF(A11="","",E11-D11) -> 894.89102 | D11: =IF(A11="","",($B$2/360*30.4)*B11) -> 4608.868 | E11: =IF(A11="","",PMT($B$2/360*30.4,$B$1,-$B$3)) -> 5503.759 | F11: =IF(A11="","",B11*Catálogos!$R$1) -> 357.89312 | G11: =IF(A11="","",IF(B11=0,0,$B$4*Catálogos!$Q$6)) -> 172.34483 | H11: =IF(A11="","",IF($G$2=1,299,0)) -> 299 | I11: =IF(A11="","",SUM(E11:H11)) -> 6332.997 | J11: =I11 -> 6332.997
A12: =IF(A11=$B$1,"",IF(A11="","",A11+1)) -> 6 | B12: =IF(A12="","",B11-C11) -> 595593.64 | C12: =IF(A12="","",E12-D12) -> 901.80555 | D12: =IF(A12="","",($B$2/360*30.4)*B12) -> 4601.9535 | E12: =IF(A12="","",PMT($B$2/360*30.4,$B$1,-$B$3)) -> 5503.759 | F12: =IF(A12="","",B12*Catálogos!$R$1) -> 357.35618 | G12: =IF(A12="","",IF(B12=0,0,$B$4*Catálogos!$Q$6)) -> 172.34483 | H12: =IF(A12="","",IF($G$2=1,299,0)) -> 299 | I12: =IF(A12="","",SUM(E12:H12)) -> 6332.4601 | J12: =I12 -> 6332.4601
A13: =IF(A12=$B$1,"",IF(A12="","",A12+1)) -> 7 | B13: =IF(A13="","",B12-C12) -> 594691.83 | C13: =IF(A13="","",E13-D13) -> 908.7735 | D13: =IF(A13="","",($B$2/360*30.4)*B13) -> 4594.9855 | E13: =IF(A13="","",PMT($B$2/360*30.4,$B$1,-$B$3)) -> 5503.759 | F13: =IF(A13="","",B13*Catálogos!$R$1) -> 356.8151 | G13: =IF(A13="","",IF(B13=0,0,$B$4*Catálogos!$Q$6)) -> 172.34483 | H13: =IF(A13="","",IF($G$2=1,299,0)) -> 299 | I13: =IF(A13="","",SUM(E13:H13)) -> 6331.919 | J13: =I13 -> 6331.919
A14: =IF(A13=$B$1,"",IF(A13="","",A13+1)) -> 8 | B14: =IF(A14="","",B13-C13) -> 593783.06 | C14: =IF(A14="","",E14-D14) -> 915.79529 | D14: =IF(A14="","",($B$2/360*30.4)*B14) -> 4587.9638 | E14: =IF(A14="","",PMT($B$2/360*30.4,$B$1,-$B$3)) -> 5503.759 | F14: =IF(A14="","",B14*Catálogos!$R$1) -> 356.26983 | G14: =IF(A14="","",IF(B14=0,0,$B$4*Catálogos!$Q$6)) -> 172.34483 | H14: =IF(A14="","",IF($G$2=1,299,0)) -> 299 | I14: =IF(A14="","",SUM(E14:H14)) -> 6331.3737 | J14: =I14 -> 6331.3737
A15: =IF(A14=$B$1,"",IF(A14="","",A14+1)) -> 9 | B15: =IF(A15="","",B14-C14) -> 592867.26 | C15: =IF(A15="","",E15-D15) -> 922.87133 | D15: =IF(A15="","",($B$2/360*30.4)*B15) -> 4580.8877 | E15: =IF(A15="","",PMT($B$2/360*30.4,$B$1,-$B$3)) -> 5503.759 | F15: =IF(A15="","",B15*Catálogos!$R$1) -> 355.72036 | G15: =IF(A15="","",IF(B15=0,0,$B$4*Catálogos!$Q$6)) -> 172.34483 | H15: =IF(A15="","",IF($G$2=1,299,0)) -> 299 | I15: =IF(A15="","",SUM(E15:H15)) -> 6330.8242 | J15: =I15 -> 6330.8242
A16: =IF(A15=$B$1,"",IF(A15="","",A15+1)) -> 10 | B16: =IF(A16="","",B15-C15) -> 591944.39 | C16: =IF(A16="","",E16-D16) -> 930.00205 | D16: =IF(A16="","",($B$2/360*30.4)*B16) -> 4573.757 | E16: =IF(A16="","",PMT($B$2/360*30.4,$B$1,-$B$3)) -> 5503.759 | F16: =IF(A16="","",B16*Catálogos!$R$1) -> 355.16663 | G16: =IF(A16="","",IF(B16=0,0,$B$4*Catálogos!$Q$6)) -> 172.34483 | H16: =IF(A16="","",IF($G$2=1,299,0)) -> 299 | I16: =IF(A16="","",SUM(E16:H16)) -> 6330.2705 | J16: =I16 -> 6330.2705
A17: =IF(A16=$B$1,"",IF(A16="","",A16+1)) -> 11 | B17: =IF(A17="","",B16-C16) -> 591014.39 | C17: =IF(A17="","",E17-D17) -> 937.18787 | D17: =IF(A17="","",($B$2/360*30.4)*B17) -> 4566.5712 | E17: =IF(A17="","",PMT($B$2/360*30.4,$B$1,-$B$3)) -> 5503.759 | F17: =IF(A17="","",B17*Catálogos!$R$1) -> 354.60863 | G17: =IF(A17="","",IF(B17=0,0,$B$4*Catálogos!$Q$6)) -> 172.34483 | H17: =IF(A17="","",IF($G$2=1,299,0)) -> 299 | I17: =IF(A17="","",SUM(E17:H17)) -> 6329.7125 | J17: =I17 -> 6329.7125
A18: =IF(A17=$B$1,"",IF(A17="","",A17+1)) -> 12 | B18: =IF(A18="","",B17-C17) -> 590077.2 | C18: =IF(A18="","",E18-D18) -> 944.42921 | D18: =IF(A18="","",($B$2/360*30.4)*B18) -> 4559.3298 | E18: =IF(A18="","",PMT($B$2/360*30.4,$B$1,-$B$3)) -> 5503.759 | F18: =IF(A18="","",B18*Catálogos!$R$1) -> 354.04632 | G18: =IF(A18="","",IF(B18=0,0,$B$4*Catálogos!$Q$6)) -> 172.34483 | H18: =IF(A18="","",IF($G$2=1,299,0)) -> 299 | I18: =IF(A18="","",SUM(E18:H18)) -> 6329.1502 | J18: =I18 -> 6329.1502
A19: =IF(A18=$B$1,"",IF(A18="","",A18+1)) -> 13 | B19: =IF(A19="","",B18-C18) -> 589132.77 | C19: =IF(A19="","",E19-D19) -> 951.7265 | D19: =IF(A19="","",($B$2/360*30.4)*B19) -> 4552.0325 | E19: =IF(A19="","",PMT($B$2/360*30.4,$B$1,-$B$3)) -> 5503.759 | F19: =IF(A19="","",B19*Catálogos!$R$1) -> 353.47966 | G19: =IF(A19="","",IF(B19=0,0,$B$4*Catálogos!$Q$6)) -> 172.34483 | H19: =IF(A19="","",IF($G$2=1,299,0)) -> 299 | I19: =IF(A19="","",SUM(E19:H19)) -> 6328.5835 | J19: =I19 -> 6328.5835
A20: =IF(A19=$B$1,"",IF(A19="","",A19+1)) -> 14 | B20: =IF(A20="","",B19-C19) -> 588181.04 | C20: =IF(A20="","",E20-D20) -> 959.08017 | D20: =IF(A20="","",($B$2/360*30.4)*B20) -> 4544.6789 | E20: =IF(A20="","",PMT($B$2/360*30.4,$B$1,-$B$3)) -> 5503.759 | F20: =IF(A20="","",B20*Catálogos!$R$1) -> 352.90863 | G20: =IF(A20="","",IF(B20=0,0,$B$4*Catálogos!$Q$6)) -> 172.34483 | H20: =IF(A20="","",IF($G$2=1,299,0)) -> 299 | I20: =IF(A20="","",SUM(E20:H20)) -> 6328.0125 | J20: =I20 -> 6328.0125
... A246: =IF(A245=$B$1,"",IF(A245="","",A245+1)) -> 240 | B246: =IF(A246="","",B245-C245) -> 5461.5594 | C246: =IF(A246="","",E246-D246) -> 5461.5594 | D246: =IF(A246="","",($B$2/360*30.4)*B246) -> 42.199649 | E246: =IF(A246="","",PMT($B$2/360*30.4,$B$1,-$B$3)) -> 5503.759 | F246: =IF(A246="","",B246*Catálogos!$R$1) -> 3.2769356 | G246: =IF(A246="","",IF(B246=0,0,$B$4*Catálogos!$Q$6)) -> 172.34483 | H246: =IF(A246="","",IF($G$2=1,299,0)) -> 299 | I246: =IF(A246="","",SUM(E246:H246)) -> 5978.3808 | J246: =I246 -> 5978.3808
